<?xml version="1.0" encoding="UTF-8" standalone="yes"?>
<w:document xmlns:wpc="http://schemas.microsoft.com/office/word/2010/wordprocessingCanvas" xmlns:mo="http://schemas.microsoft.com/office/mac/office/2008/main" xmlns:mc="http://schemas.openxmlformats.org/markup-compatibility/2006" xmlns:mv="urn:schemas-microsoft-com:mac:vml" xmlns:o="urn:schemas-microsoft-com:office:office" xmlns:r="http://schemas.openxmlformats.org/officeDocument/2006/relationships" xmlns:m="http://schemas.openxmlformats.org/officeDocument/2006/math" xmlns:v="urn:schemas-microsoft-com:vml" xmlns:wp14="http://schemas.microsoft.com/office/word/2010/wordprocessingDrawing" xmlns:wp="http://schemas.openxmlformats.org/drawingml/2006/wordprocessingDrawing" xmlns:w10="urn:schemas-microsoft-com:office:word" xmlns:w="http://schemas.openxmlformats.org/wordprocessingml/2006/main" xmlns:w14="http://schemas.microsoft.com/office/word/2010/wordml" xmlns:wpg="http://schemas.microsoft.com/office/word/2010/wordprocessingGroup" xmlns:wpi="http://schemas.microsoft.com/office/word/2010/wordprocessingInk" xmlns:wne="http://schemas.microsoft.com/office/word/2006/wordml" xmlns:wps="http://schemas.microsoft.com/office/word/2010/wordprocessingShape" mc:Ignorable="w14 wp14"><w:body><w:p w14:paraId="673FD5A2" w14:textId="77777777" w:rsidR="00683359" w:rsidRPr="00683359" w:rsidRDefault="00683359" w:rsidP="00683359"><w:pPr><w:spacing w:after="0" w:line="240" w:lineRule="auto"/><w:jc w:val="center"/><w:rPr><w:rFonts w:ascii="Times" w:hAnsi="Times"/><w:b/><w:bCs/><w:sz w:val="28"/><w:szCs w:val="28"/><w:lang w:eastAsia="en-US"/></w:rPr></w:pPr><w:r w:rsidRPr="00683359"><w:rPr><w:rFonts w:ascii="Times" w:hAnsi="Times"/><w:b/><w:bCs/><w:sz w:val="28"/><w:szCs w:val="28"/><w:lang w:eastAsia="en-US"/></w:rPr><w:t xml:space="preserve">Opinion Mining and Sentiment Analysis of </w:t></w:r><w:proofErr w:type="spellStart"/><w:r w:rsidRPr="00683359"><w:rPr><w:rFonts w:ascii="Times" w:hAnsi="Times"/><w:b/><w:bCs/><w:sz w:val="28"/><w:szCs w:val="28"/><w:lang w:eastAsia="en-US"/></w:rPr><w:t>TripAdvisor</w:t></w:r><w:proofErr w:type="spellEnd"/><w:r w:rsidRPr="00683359"><w:rPr><w:rFonts w:ascii="Times" w:hAnsi="Times"/><w:b/><w:bCs/><w:sz w:val="28"/><w:szCs w:val="28"/><w:lang w:eastAsia="en-US"/></w:rPr><w:t xml:space="preserve"> Hotel Reviews</w:t></w:r></w:p><w:p w14:paraId="16F3A848" w14:textId="77777777" w:rsidR="00683359" w:rsidRDefault="00683359" w:rsidP="00683359"><w:pPr><w:spacing w:after="0" w:line="240" w:lineRule="auto"/><w:jc w:val="center"/><w:rPr><w:sz w:val="24"/><w:szCs w:val="24"/></w:rPr></w:pPr><w:r w:rsidRPr="00683359"><w:rPr><w:sz w:val="24"/><w:szCs w:val="24"/></w:rPr><w:t xml:space="preserve">Group members: Jason </w:t></w:r><w:proofErr w:type="gramStart"/><w:r w:rsidRPr="00683359"><w:rPr><w:sz w:val="24"/><w:szCs w:val="24"/></w:rPr><w:t>Cai</w:t></w:r><w:proofErr w:type="gramEnd"/><w:r w:rsidRPr="00683359"><w:rPr><w:sz w:val="24"/><w:szCs w:val="24"/></w:rPr><w:t xml:space="preserve">, Toby Du, </w:t></w:r><w:proofErr w:type="spellStart"/><w:r w:rsidRPr="00683359"><w:rPr><w:sz w:val="24"/><w:szCs w:val="24"/></w:rPr><w:t>Peiheng</w:t></w:r><w:proofErr w:type="spellEnd"/><w:r w:rsidRPr="00683359"><w:rPr><w:sz w:val="24"/><w:szCs w:val="24"/></w:rPr><w:t xml:space="preserve"> Hu, </w:t></w:r><w:proofErr w:type="spellStart"/><w:r w:rsidRPr="00683359"><w:rPr><w:sz w:val="24"/><w:szCs w:val="24"/></w:rPr><w:t>Arjun</w:t></w:r><w:proofErr w:type="spellEnd"/><w:r w:rsidRPr="00683359"><w:rPr><w:sz w:val="24"/><w:szCs w:val="24"/></w:rPr><w:t xml:space="preserve"> </w:t></w:r><w:proofErr w:type="spellStart"/><w:r w:rsidRPr="00683359"><w:rPr><w:sz w:val="24"/><w:szCs w:val="24"/></w:rPr><w:t>Sanghvi</w:t></w:r><w:proofErr w:type="spellEnd"/></w:p><w:p w14:paraId="1C8B925F" w14:textId="77777777" w:rsidR="00683359" w:rsidRPr="00683359" w:rsidRDefault="00683359" w:rsidP="00683359"><w:pPr><w:spacing w:after="0" w:line="240" w:lineRule="auto"/><w:jc w:val="center"/><w:rPr><w:sz w:val="24"/><w:szCs w:val="24"/></w:rPr></w:pPr><w:r><w:rPr><w:sz w:val="24"/><w:szCs w:val="24"/></w:rPr><w:t>Institution of Applied Computational Science, Harvard University</w:t></w:r></w:p><w:p w14:paraId="317B138A" w14:textId="77777777" w:rsidR="00683359" w:rsidRPr="00800EF3" w:rsidRDefault="00683359" w:rsidP="00683359"><w:pPr><w:spacing w:after="0" w:line="240" w:lineRule="auto"/><w:jc w:val="center"/><w:rPr><w:b/><w:sz w:val="12"/><w:szCs w:val="12"/></w:rPr></w:pPr></w:p><w:p w14:paraId="59A9647B" w14:textId="77777777" w:rsidR="00683359" w:rsidRDefault="00683359" w:rsidP="00683359"><w:pPr><w:spacing w:after="0" w:line="240" w:lineRule="auto"/><w:rPr><w:sz w:val="24"/><w:szCs w:val="24"/></w:rPr></w:pPr></w:p><w:p w14:paraId="5280AA3C" w14:textId="77777777" w:rsidR="00683359" w:rsidRDefault="00683359" w:rsidP="00683359"><w:pPr><w:spacing w:after="0" w:line="240" w:lineRule="auto"/><w:rPr><w:sz w:val="24"/><w:szCs w:val="24"/></w:rPr></w:pPr></w:p><w:p w14:paraId="2D0F9AB0" w14:textId="77777777" w:rsidR="00683359" w:rsidRPr="00BA593B" w:rsidRDefault="00683359" w:rsidP="00681FA2"><w:pPr><w:jc w:val="both"/><w:rPr><w:rFonts w:ascii="Times" w:hAnsi="Times"/><w:b/><w:sz w:val="30"/><w:szCs w:val="30"/><w:u w:val="single"/></w:rPr></w:pPr><w:r w:rsidRPr="00BA593B"><w:rPr><w:rFonts w:ascii="Times" w:hAnsi="Times"/><w:b/><w:sz w:val="30"/><w:szCs w:val="30"/><w:u w:val="single"/></w:rPr><w:t>Introduction</w:t></w:r></w:p><w:p w14:paraId="4AAE1213" w14:textId="77777777" w:rsidR="00683359" w:rsidRDefault="00683359" w:rsidP="00681FA2"><w:pPr><w:spacing w:after="0" w:line="240" w:lineRule="auto"/><w:jc w:val="both"/><w:rPr><w:sz w:val="24"/><w:szCs w:val="24"/></w:rPr></w:pPr><w:proofErr w:type="spellStart"/><w:r w:rsidRPr="003341D4"><w:rPr><w:sz w:val="24"/><w:szCs w:val="24"/></w:rPr><w:t>TripAdvisor</w:t></w:r><w:proofErr w:type="spellEnd"/><w:r w:rsidRPr="003341D4"><w:rPr><w:sz w:val="24"/><w:szCs w:val="24"/></w:rPr><w:t>, founded in 2000, is a public company that operates various travel website</w:t></w:r><w:r><w:rPr><w:sz w:val="24"/><w:szCs w:val="24"/></w:rPr><w:t>s</w:t></w:r><w:r w:rsidRPr="003341D4"><w:rPr><w:sz w:val="24"/><w:szCs w:val="24"/></w:rPr><w:t xml:space="preserve"> providing </w:t></w:r><w:r><w:rPr><w:sz w:val="24"/><w:szCs w:val="24"/></w:rPr><w:t>travel-related content, such as editorial reviews of hotels, in addition to providing a free forum for user discussion. The company has about 2400 e</w:t></w:r><w:r w:rsidRPr="003341D4"><w:rPr><w:sz w:val="24"/><w:szCs w:val="24"/></w:rPr><w:t>mployees worldwide</w:t></w:r><w:r><w:rPr><w:sz w:val="24"/><w:szCs w:val="24"/></w:rPr><w:t>,</w:t></w:r><w:r w:rsidRPr="003341D4"><w:rPr><w:sz w:val="24"/><w:szCs w:val="24"/></w:rPr><w:t xml:space="preserve"> and websites </w:t></w:r><w:r><w:rPr><w:sz w:val="24"/><w:szCs w:val="24"/></w:rPr><w:t xml:space="preserve">that are part of the </w:t></w:r><w:proofErr w:type="spellStart"/><w:r><w:rPr><w:sz w:val="24"/><w:szCs w:val="24"/></w:rPr><w:t>TripAdvisor</w:t></w:r><w:proofErr w:type="spellEnd"/><w:r><w:rPr><w:sz w:val="24"/><w:szCs w:val="24"/></w:rPr><w:t xml:space="preserve"> Group attract</w:t></w:r><w:r w:rsidRPr="003341D4"><w:rPr><w:sz w:val="24"/><w:szCs w:val="24"/></w:rPr><w:t xml:space="preserve"> greater</w:t></w:r><w:r><w:rPr><w:sz w:val="24"/><w:szCs w:val="24"/></w:rPr><w:t xml:space="preserve"> than 100 million monthly views. While revenue is primarily generated through advertising, user-generated content (such as photographs, ratings, and reviews) has become the backbone of the company. </w:t></w:r><w:proofErr w:type="spellStart"/><w:r><w:rPr><w:sz w:val="24"/><w:szCs w:val="24"/></w:rPr><w:t>TripAdvisor</w:t></w:r><w:proofErr w:type="spellEnd"/><w:r><w:rPr><w:sz w:val="24"/><w:szCs w:val="24"/></w:rPr><w:t xml:space="preserve"> has become such an integral part of travel business worldwide, that it holds enough sway to single-handedly make or break a hotel depending on how that hotel is portrayed on the Trip Advisor website. </w:t></w:r><w:proofErr w:type="spellStart"/><w:r w:rsidRPr="003341D4"><w:rPr><w:sz w:val="24"/><w:szCs w:val="24"/></w:rPr><w:t>SmarterTravel</w:t></w:r><w:proofErr w:type="spellEnd"/><w:r w:rsidRPr="003341D4"><w:rPr><w:sz w:val="24"/><w:szCs w:val="24"/></w:rPr><w:t>, founded in 1998</w:t></w:r><w:r><w:rPr><w:sz w:val="24"/><w:szCs w:val="24"/></w:rPr><w:t xml:space="preserve"> and </w:t></w:r><w:r w:rsidRPr="003341D4"><w:rPr><w:sz w:val="24"/><w:szCs w:val="24"/></w:rPr><w:t xml:space="preserve">acquired by </w:t></w:r><w:proofErr w:type="spellStart"/><w:r w:rsidRPr="003341D4"><w:rPr><w:sz w:val="24"/><w:szCs w:val="24"/></w:rPr><w:t>TripAdv</w:t></w:r><w:r><w:rPr><w:sz w:val="24"/><w:szCs w:val="24"/></w:rPr><w:t>isor</w:t></w:r><w:proofErr w:type="spellEnd"/><w:r><w:rPr><w:sz w:val="24"/><w:szCs w:val="24"/></w:rPr><w:t xml:space="preserve"> in 2007</w:t></w:r><w:r w:rsidRPr="003341D4"><w:rPr><w:sz w:val="24"/><w:szCs w:val="24"/></w:rPr><w:t xml:space="preserve">, offers a portfolio of travel sites </w:t></w:r><w:r><w:rPr><w:sz w:val="24"/><w:szCs w:val="24"/></w:rPr><w:t xml:space="preserve">that can be searched simultaneously to explore prices. Jetsetter, founded in 2009 and acquired by </w:t></w:r><w:proofErr w:type="spellStart"/><w:r><w:rPr><w:sz w:val="24"/><w:szCs w:val="24"/></w:rPr><w:t>TripAdvisor</w:t></w:r><w:proofErr w:type="spellEnd"/><w:r><w:rPr><w:sz w:val="24"/><w:szCs w:val="24"/></w:rPr><w:t xml:space="preserve"> in 2013, acts as an online travel agency catering to customers searching for higher quality (higher price) accommodations.</w:t></w:r></w:p><w:p w14:paraId="12F84F54" w14:textId="77777777" w:rsidR="00683359" w:rsidRDefault="00683359" w:rsidP="00A60A9B"><w:pPr><w:spacing w:after="0" w:line="240" w:lineRule="auto"/><w:jc w:val="both"/><w:rPr><w:sz w:val="24"/><w:szCs w:val="24"/></w:rPr></w:pPr></w:p><w:p w14:paraId="5B07F69F" w14:textId="77777777" w:rsidR="00683359" w:rsidRDefault="00683359" w:rsidP="00681FA2"><w:pPr><w:spacing w:after="0" w:line="240" w:lineRule="auto"/><w:jc w:val="both"/><w:rPr><w:sz w:val="24"/><w:szCs w:val="24"/></w:rPr></w:pPr><w:r><w:rPr><w:sz w:val="24"/><w:szCs w:val="24"/></w:rPr><w:t>The massive amount of user-generated content posted on Trip Advisor is an invaluable resource of feedback for hotels and Trip Advisor itself. With this feedback, Trip Advisor can conduct internal improvement efforts, in addition to working with hotels to improve the customer experience. To date, Trip Advisor has used the labor intensive and potentially biased method of manually analyzing a small subset of the reviews. The goal of this project, therefore, is to construct an automated system (software) for analyzing free-form text responses. The output of this analysis will include extraction of informative word pairs (e.g. “great location”) in addition to calculation of a sentiment score. Further details are given below.</w:t></w:r></w:p><w:p w14:paraId="5B8D18F0" w14:textId="77777777" w:rsidR="00683359" w:rsidRDefault="00683359" w:rsidP="00681FA2"><w:pPr><w:spacing w:after="0" w:line="240" w:lineRule="auto"/><w:jc w:val="both"/><w:rPr><w:sz w:val="24"/><w:szCs w:val="24"/></w:rPr></w:pPr></w:p><w:p w14:paraId="6C126EBD" w14:textId="77777777" w:rsidR="009F1D1C" w:rsidRDefault="009F1D1C" w:rsidP="00681FA2"><w:pPr><w:spacing w:after="0" w:line="240" w:lineRule="auto"/><w:jc w:val="both"/><w:rPr><w:sz w:val="24"/><w:szCs w:val="24"/></w:rPr></w:pPr></w:p><w:p w14:paraId="16AE217A" w14:textId="3147120C" w:rsidR="009F1D1C" w:rsidRPr="00BA593B" w:rsidRDefault="009F1D1C" w:rsidP="00681FA2"><w:pPr><w:jc w:val="both"/><w:rPr><w:rFonts w:ascii="Times" w:hAnsi="Times"/><w:b/><w:bCs/><w:sz w:val="30"/><w:szCs w:val="30"/><w:u w:val="single"/></w:rPr></w:pPr><w:r w:rsidRPr="00BA593B"><w:rPr><w:rFonts w:ascii="Times" w:hAnsi="Times"/><w:b/><w:bCs/><w:sz w:val="30"/><w:szCs w:val="30"/><w:u w:val="single"/></w:rPr><w:t xml:space="preserve">Dataset </w:t></w:r></w:p><w:p w14:paraId="4F028D99" w14:textId="23A63F86" w:rsidR="00683359" w:rsidRDefault="00683359" w:rsidP="00681FA2"><w:pPr><w:spacing w:after="0" w:line="240" w:lineRule="auto"/><w:jc w:val="both"/><w:rPr><w:sz w:val="24"/><w:szCs w:val="24"/></w:rPr></w:pPr><w:r><w:rPr><w:sz w:val="24"/><w:szCs w:val="24"/></w:rPr><w:t>The data set used in this project is comprised of</w:t></w:r><w:r w:rsidRPr="003341D4"><w:rPr><w:sz w:val="24"/><w:szCs w:val="24"/></w:rPr><w:t xml:space="preserve"> Jetsetter reviews</w:t></w:r><w:r><w:rPr><w:sz w:val="24"/><w:szCs w:val="24"/></w:rPr><w:t>, which contain user responses to the following questions for a given hotel</w:t></w:r><w:r w:rsidR="00681FA2"><w:rPr><w:sz w:val="24"/><w:szCs w:val="24"/></w:rPr><w:t>’s</w:t></w:r><w:r><w:rPr><w:sz w:val="24"/><w:szCs w:val="24"/></w:rPr><w:t xml:space="preserve"> experience: “what did you love” and “w</w:t></w:r><w:r w:rsidRPr="003341D4"><w:rPr><w:sz w:val="24"/><w:szCs w:val="24"/></w:rPr><w:t xml:space="preserve">hat </w:t></w:r><w:r><w:rPr><w:sz w:val="24"/><w:szCs w:val="24"/></w:rPr><w:t>should others</w:t></w:r><w:r w:rsidRPr="003341D4"><w:rPr><w:sz w:val="24"/><w:szCs w:val="24"/></w:rPr><w:t xml:space="preserve"> know</w:t></w:r><w:r><w:rPr><w:sz w:val="24"/><w:szCs w:val="24"/></w:rPr><w:t>”</w:t></w:r><w:r w:rsidR="000104D1"><w:rPr><w:sz w:val="24"/><w:szCs w:val="24"/></w:rPr><w:t>. Basically, “what did you love” contains responses that are positive to the hotel or Jet Setter and “w</w:t></w:r><w:r w:rsidR="000104D1" w:rsidRPr="003341D4"><w:rPr><w:sz w:val="24"/><w:szCs w:val="24"/></w:rPr><w:t xml:space="preserve">hat </w:t></w:r><w:r w:rsidR="000104D1"><w:rPr><w:sz w:val="24"/><w:szCs w:val="24"/></w:rPr><w:t>should others</w:t></w:r><w:r w:rsidR="000104D1" w:rsidRPr="003341D4"><w:rPr><w:sz w:val="24"/><w:szCs w:val="24"/></w:rPr><w:t xml:space="preserve"> </w:t></w:r><w:r w:rsidR="000104D1"><w:rPr><w:sz w:val="24"/><w:szCs w:val="24"/></w:rPr><w:t>know</w:t></w:r><w:proofErr w:type="gramStart"/><w:r w:rsidR="000104D1"><w:rPr><w:sz w:val="24"/><w:szCs w:val="24"/></w:rPr><w:t>”</w:t></w:r><w:proofErr w:type="gramEnd"/><w:r w:rsidR="000104D1"><w:rPr><w:sz w:val="24"/><w:szCs w:val="24"/></w:rPr><w:t xml:space="preserve"> reflects the negative complaints.</w:t></w:r><w:r><w:rPr><w:sz w:val="24"/><w:szCs w:val="24"/></w:rPr><w:t xml:space="preserve"> The data set we currently have contains 100,000 reviews representing 3000 hotels from </w:t></w:r><w:r w:rsidR="00681FA2"><w:rPr><w:sz w:val="24"/><w:szCs w:val="24"/></w:rPr><w:t>all over the world</w:t></w:r><w:r><w:rPr><w:sz w:val="24"/><w:szCs w:val="24"/></w:rPr><w:t xml:space="preserve">. </w:t></w:r></w:p><w:p w14:paraId="2FFEFB54" w14:textId="77777777" w:rsidR="00683359" w:rsidRDefault="00683359" w:rsidP="00681FA2"><w:pPr><w:spacing w:after="0" w:line="240" w:lineRule="auto"/><w:jc w:val="both"/><w:rPr><w:sz w:val="24"/><w:szCs w:val="24"/></w:rPr></w:pPr></w:p><w:p w14:paraId="500C2D55" w14:textId="77777777" w:rsidR="0088429A" w:rsidRDefault="0088429A" w:rsidP="00681FA2"><w:pPr><w:spacing w:after="0" w:line="240" w:lineRule="auto"/><w:jc w:val="both"/><w:rPr><w:sz w:val="24"/><w:szCs w:val="24"/></w:rPr></w:pPr></w:p><w:p w14:paraId="7E340837" w14:textId="4B9DFC5E" w:rsidR="0088429A" w:rsidRPr="00BA593B" w:rsidRDefault="0088429A" w:rsidP="00681FA2"><w:pPr><w:jc w:val="both"/><w:rPr><w:rFonts w:ascii="Times" w:hAnsi="Times"/><w:b/><w:sz w:val="30"/><w:szCs w:val="30"/><w:u w:val="single"/></w:rPr></w:pPr><w:r w:rsidRPr="00BA593B"><w:rPr><w:rFonts w:ascii="Times" w:hAnsi="Times"/><w:b/><w:sz w:val="30"/><w:szCs w:val="30"/><w:u w:val="single"/></w:rPr><w:t xml:space="preserve">Goal </w:t></w:r></w:p><w:p w14:paraId="63FC89B3" w14:textId="021DFBCA" w:rsidR="00683359" w:rsidRDefault="00683359" w:rsidP="00681FA2"><w:pPr><w:spacing w:after="0" w:line="240" w:lineRule="auto"/><w:jc w:val="both"/><w:rPr><w:sz w:val="24"/><w:szCs w:val="24"/></w:rPr></w:pPr><w:r><w:rPr><w:sz w:val="24"/><w:szCs w:val="24"/></w:rPr><w:t xml:space="preserve">The goal of this project is to achieve an output that, for a given hotel, </w:t></w:r><w:r w:rsidR="00F925FE"><w:rPr><w:sz w:val="24"/><w:szCs w:val="24"/></w:rPr><w:t>the summary should look</w:t></w:r><w:r><w:rPr><w:sz w:val="24"/><w:szCs w:val="24"/></w:rPr><w:t xml:space="preserve"> like</w:t></w:r><w:r w:rsidR="00F925FE"><w:rPr><w:sz w:val="24"/><w:szCs w:val="24"/></w:rPr><w:t xml:space="preserve"> below</w:t></w:r><w:r><w:rPr><w:sz w:val="24"/><w:szCs w:val="24"/></w:rPr><w:t>:</w:t></w:r></w:p><w:p w14:paraId="6A3B7D1A" w14:textId="77777777" w:rsidR="00683359" w:rsidRDefault="00683359" w:rsidP="00BA593B"><w:pPr><w:spacing w:after="0" w:line="240" w:lineRule="auto"/><w:jc w:val="both"/><w:rPr><w:rFonts w:hAnsi="Calibri"/><w:b/><w:bCs/><w:color w:val="000000" w:themeColor="text1"/><w:kern w:val="24"/><w:sz w:val="24"/><w:szCs w:val="24"/></w:rPr></w:pPr><w:r><w:rPr><w:rFonts w:hAnsi="Calibri"/><w:b/><w:bCs/><w:color w:val="000000" w:themeColor="text1"/><w:kern w:val="24"/><w:sz w:val="24"/><w:szCs w:val="24"/></w:rPr><w:lastRenderedPageBreak/><w:t>Hotel ID</w:t></w:r><w:r w:rsidRPr="00832718"><w:rPr><w:rFonts w:hAnsi="Calibri"/><w:b/><w:bCs/><w:color w:val="000000" w:themeColor="text1"/><w:kern w:val="24"/><w:sz w:val="24"/><w:szCs w:val="24"/></w:rPr><w:t>: 1234</w:t></w:r></w:p><w:p w14:paraId="25132286" w14:textId="77777777" w:rsidR="00AC4DC8" w:rsidRPr="00832718" w:rsidRDefault="00AC4DC8" w:rsidP="00681FA2"><w:pPr><w:spacing w:after="0" w:line="240" w:lineRule="auto"/><w:ind w:left="360" w:hanging="360"/><w:jc w:val="both"/><w:rPr><w:rFonts w:eastAsia="Times New Roman" w:cs="Times New Roman"/><w:sz w:val="24"/><w:szCs w:val="24"/></w:rPr></w:pPr></w:p><w:p w14:paraId="073B4FED" w14:textId="77777777" w:rsidR="00683359" w:rsidRPr="00832718" w:rsidRDefault="00683359" w:rsidP="00681FA2"><w:pPr><w:spacing w:after="0" w:line="240" w:lineRule="auto"/><w:jc w:val="both"/><w:rPr><w:rFonts w:eastAsia="Times New Roman" w:cs="Times New Roman"/><w:sz w:val="24"/><w:szCs w:val="24"/></w:rPr></w:pPr><w:r w:rsidRPr="00832718"><w:rPr><w:rFonts w:hAnsi="Calibri"/><w:b/><w:bCs/><w:color w:val="000000" w:themeColor="text1"/><w:kern w:val="24"/><w:sz w:val="24"/><w:szCs w:val="24"/></w:rPr><w:t>Total number of reviews: 125</w:t></w:r></w:p><w:p w14:paraId="49D5E5BB" w14:textId="77777777" w:rsidR="00490386" w:rsidRDefault="00490386" w:rsidP="00681FA2"><w:pPr><w:spacing w:after="0" w:line="240" w:lineRule="auto"/><w:ind w:left="360" w:hanging="360"/><w:jc w:val="both"/><w:rPr><w:rFonts w:hAnsi="Calibri"/><w:b/><w:bCs/><w:color w:val="000000" w:themeColor="text1"/><w:kern w:val="24"/><w:sz w:val="24"/><w:szCs w:val="24"/></w:rPr></w:pPr></w:p><w:p w14:paraId="0975E5C8" w14:textId="77777777" w:rsidR="00683359" w:rsidRPr="00832718" w:rsidRDefault="00683359" w:rsidP="00681FA2"><w:pPr><w:spacing w:after="0" w:line="240" w:lineRule="auto"/><w:ind w:left="360" w:hanging="360"/><w:jc w:val="both"/><w:rPr><w:rFonts w:eastAsia="Times New Roman" w:cs="Times New Roman"/><w:sz w:val="24"/><w:szCs w:val="24"/></w:rPr></w:pPr><w:r w:rsidRPr="00832718"><w:rPr><w:rFonts w:hAnsi="Calibri"/><w:b/><w:bCs/><w:color w:val="000000" w:themeColor="text1"/><w:kern w:val="24"/><w:sz w:val="24"/><w:szCs w:val="24"/></w:rPr><w:t>Rooms (0.75 score, 75 comments)</w:t></w:r></w:p><w:p w14:paraId="0AFCE35B" w14:textId="77777777" w:rsidR="00683359" w:rsidRPr="00832718" w:rsidRDefault="00683359" w:rsidP="00681FA2"><w:pPr><w:pStyle w:val="NormalWeb"/><w:spacing w:before="0" w:beforeAutospacing="0" w:after="0" w:afterAutospacing="0"/><w:ind w:left="1080" w:hanging="360"/><w:jc w:val="both"/><w:rPr><w:sz w:val="24"/><w:szCs w:val="24"/></w:rPr></w:pPr><w:r w:rsidRPr="00832718"><w:rPr><w:rFonts w:asciiTheme="minorHAnsi" w:hAnsi="Calibri" w:cstheme="minorBidi"/><w:color w:val="000000" w:themeColor="text1"/><w:kern w:val="24"/><w:sz w:val="24"/><w:szCs w:val="24"/></w:rPr><w:t>(+) What your hotel is good at:</w:t></w:r></w:p><w:p w14:paraId="22AAC84B" w14:textId="77777777" w:rsidR="00683359" w:rsidRPr="00832718" w:rsidRDefault="00683359" w:rsidP="00681FA2"><w:pPr><w:pStyle w:val="NormalWeb"/><w:spacing w:before="0" w:beforeAutospacing="0" w:after="0" w:afterAutospacing="0"/><w:ind w:left="1080" w:hanging="360"/><w:jc w:val="both"/><w:rPr><w:sz w:val="24"/><w:szCs w:val="24"/></w:rPr></w:pPr><w:r w:rsidRPr="00832718"><w:rPr><w:rFonts w:asciiTheme="minorHAnsi" w:hAnsi="Calibri" w:cstheme="minorBidi"/><w:color w:val="000000" w:themeColor="text1"/><w:kern w:val="24"/><w:sz w:val="24"/><w:szCs w:val="24"/></w:rPr><w:t>(</w:t></w:r><w:proofErr w:type="gramStart"/><w:r w:rsidRPr="00832718"><w:rPr><w:rFonts w:asciiTheme="minorHAnsi" w:hAnsi="Calibri" w:cstheme="minorBidi"/><w:color w:val="000000" w:themeColor="text1"/><w:kern w:val="24"/><w:sz w:val="24"/><w:szCs w:val="24"/></w:rPr><w:t>wonderful</w:t></w:r><w:proofErr w:type="gramEnd"/><w:r w:rsidRPr="00832718"><w:rPr><w:rFonts w:asciiTheme="minorHAnsi" w:hAnsi="Calibri" w:cstheme="minorBidi"/><w:color w:val="000000" w:themeColor="text1"/><w:kern w:val="24"/><w:sz w:val="24"/><w:szCs w:val="24"/></w:rPr><w:t xml:space="preserve"> view), (luxurious bed)</w:t></w:r></w:p><w:p w14:paraId="0CD29B7F" w14:textId="77777777" w:rsidR="00683359" w:rsidRPr="00832718" w:rsidRDefault="00683359" w:rsidP="00681FA2"><w:pPr><w:pStyle w:val="NormalWeb"/><w:spacing w:before="0" w:beforeAutospacing="0" w:after="0" w:afterAutospacing="0"/><w:ind w:left="1080" w:hanging="360"/><w:jc w:val="both"/><w:rPr><w:sz w:val="24"/><w:szCs w:val="24"/></w:rPr></w:pPr><w:r w:rsidRPr="00832718"><w:rPr><w:rFonts w:asciiTheme="minorHAnsi" w:hAnsi="Calibri" w:cstheme="minorBidi"/><w:color w:val="000000" w:themeColor="text1"/><w:kern w:val="24"/><w:sz w:val="24"/><w:szCs w:val="24"/></w:rPr><w:t xml:space="preserve"> (-) Most frequent complaints:</w:t></w:r></w:p><w:p w14:paraId="06A41E19" w14:textId="77777777" w:rsidR="00683359" w:rsidRPr="00832718" w:rsidRDefault="00683359" w:rsidP="00681FA2"><w:pPr><w:pStyle w:val="NormalWeb"/><w:spacing w:before="0" w:beforeAutospacing="0" w:after="0" w:afterAutospacing="0"/><w:ind w:left="1080" w:hanging="360"/><w:jc w:val="both"/><w:rPr><w:sz w:val="24"/><w:szCs w:val="24"/></w:rPr></w:pPr><w:r w:rsidRPr="00832718"><w:rPr><w:rFonts w:asciiTheme="minorHAnsi" w:hAnsi="Calibri" w:cstheme="minorBidi"/><w:color w:val="000000" w:themeColor="text1"/><w:kern w:val="24"/><w:sz w:val="24"/><w:szCs w:val="24"/></w:rPr><w:t>(</w:t></w:r><w:proofErr w:type="gramStart"/><w:r w:rsidRPr="00832718"><w:rPr><w:rFonts w:asciiTheme="minorHAnsi" w:hAnsi="Calibri" w:cstheme="minorBidi"/><w:color w:val="000000" w:themeColor="text1"/><w:kern w:val="24"/><w:sz w:val="24"/><w:szCs w:val="24"/></w:rPr><w:t>scratchy</w:t></w:r><w:proofErr w:type="gramEnd"/><w:r w:rsidRPr="00832718"><w:rPr><w:rFonts w:asciiTheme="minorHAnsi" w:hAnsi="Calibri" w:cstheme="minorBidi"/><w:color w:val="000000" w:themeColor="text1"/><w:kern w:val="24"/><w:sz w:val="24"/><w:szCs w:val="24"/></w:rPr><w:t xml:space="preserve"> towels), (small TV)</w:t></w:r></w:p><w:p w14:paraId="66B414C6" w14:textId="77777777" w:rsidR="00AC0C13" w:rsidRDefault="00AC0C13" w:rsidP="00681FA2"><w:pPr><w:spacing w:after="0" w:line="240" w:lineRule="auto"/><w:ind w:left="360" w:hanging="360"/><w:jc w:val="both"/><w:rPr><w:rFonts w:hAnsi="Calibri"/><w:b/><w:bCs/><w:color w:val="000000" w:themeColor="text1"/><w:kern w:val="24"/><w:sz w:val="24"/><w:szCs w:val="24"/></w:rPr></w:pPr></w:p><w:p w14:paraId="61235915" w14:textId="77777777" w:rsidR="00683359" w:rsidRPr="00832718" w:rsidRDefault="00683359" w:rsidP="00681FA2"><w:pPr><w:spacing w:after="0" w:line="240" w:lineRule="auto"/><w:ind w:left="360" w:hanging="360"/><w:jc w:val="both"/><w:rPr><w:rFonts w:eastAsia="Times New Roman" w:cs="Times New Roman"/><w:sz w:val="24"/><w:szCs w:val="24"/></w:rPr></w:pPr><w:r w:rsidRPr="00832718"><w:rPr><w:rFonts w:hAnsi="Calibri"/><w:b/><w:bCs/><w:color w:val="000000" w:themeColor="text1"/><w:kern w:val="24"/><w:sz w:val="24"/><w:szCs w:val="24"/></w:rPr><w:t>Service (0.82 score, 51 comments)</w:t></w:r></w:p><w:p w14:paraId="241D56B8" w14:textId="77777777" w:rsidR="00683359" w:rsidRPr="00832718" w:rsidRDefault="00683359" w:rsidP="00681FA2"><w:pPr><w:pStyle w:val="NormalWeb"/><w:spacing w:before="0" w:beforeAutospacing="0" w:after="0" w:afterAutospacing="0"/><w:ind w:left="1080" w:hanging="360"/><w:jc w:val="both"/><w:rPr><w:sz w:val="24"/><w:szCs w:val="24"/></w:rPr></w:pPr><w:r w:rsidRPr="00832718"><w:rPr><w:rFonts w:asciiTheme="minorHAnsi" w:hAnsi="Calibri" w:cstheme="minorBidi"/><w:color w:val="000000" w:themeColor="text1"/><w:kern w:val="24"/><w:sz w:val="24"/><w:szCs w:val="24"/></w:rPr><w:t>(+) What your hotel is good at:</w:t></w:r></w:p><w:p w14:paraId="14948D64" w14:textId="77777777" w:rsidR="00683359" w:rsidRPr="00832718" w:rsidRDefault="00683359" w:rsidP="00681FA2"><w:pPr><w:pStyle w:val="NormalWeb"/><w:spacing w:before="0" w:beforeAutospacing="0" w:after="0" w:afterAutospacing="0"/><w:ind w:left="1080" w:hanging="360"/><w:jc w:val="both"/><w:rPr><w:sz w:val="24"/><w:szCs w:val="24"/></w:rPr></w:pPr><w:r w:rsidRPr="00832718"><w:rPr><w:rFonts w:asciiTheme="minorHAnsi" w:hAnsi="Calibri" w:cstheme="minorBidi"/><w:color w:val="000000" w:themeColor="text1"/><w:kern w:val="24"/><w:sz w:val="24"/><w:szCs w:val="24"/></w:rPr><w:t>(</w:t></w:r><w:proofErr w:type="gramStart"/><w:r w:rsidRPr="00832718"><w:rPr><w:rFonts w:asciiTheme="minorHAnsi" w:hAnsi="Calibri" w:cstheme="minorBidi"/><w:color w:val="000000" w:themeColor="text1"/><w:kern w:val="24"/><w:sz w:val="24"/><w:szCs w:val="24"/></w:rPr><w:t>caring</w:t></w:r><w:proofErr w:type="gramEnd"/><w:r w:rsidRPr="00832718"><w:rPr><w:rFonts w:asciiTheme="minorHAnsi" w:hAnsi="Calibri" w:cstheme="minorBidi"/><w:color w:val="000000" w:themeColor="text1"/><w:kern w:val="24"/><w:sz w:val="24"/><w:szCs w:val="24"/></w:rPr><w:t xml:space="preserve"> staff), (excellent service)</w:t></w:r></w:p><w:p w14:paraId="2200DFD1" w14:textId="77777777" w:rsidR="00683359" w:rsidRPr="00832718" w:rsidRDefault="00683359" w:rsidP="00681FA2"><w:pPr><w:pStyle w:val="NormalWeb"/><w:spacing w:before="0" w:beforeAutospacing="0" w:after="0" w:afterAutospacing="0"/><w:ind w:left="1080" w:hanging="360"/><w:jc w:val="both"/><w:rPr><w:sz w:val="24"/><w:szCs w:val="24"/></w:rPr></w:pPr><w:r w:rsidRPr="00832718"><w:rPr><w:rFonts w:asciiTheme="minorHAnsi" w:hAnsi="Calibri" w:cstheme="minorBidi"/><w:color w:val="000000" w:themeColor="text1"/><w:kern w:val="24"/><w:sz w:val="24"/><w:szCs w:val="24"/></w:rPr><w:t>(-) Most frequent complaints:</w:t></w:r></w:p><w:p w14:paraId="16970808" w14:textId="77777777" w:rsidR="00683359" w:rsidRDefault="00683359" w:rsidP="00681FA2"><w:pPr><w:pStyle w:val="NormalWeb"/><w:spacing w:before="0" w:beforeAutospacing="0" w:after="0" w:afterAutospacing="0"/><w:ind w:left="1080" w:hanging="360"/><w:jc w:val="both"/><w:rPr><w:rFonts w:asciiTheme="minorHAnsi" w:hAnsi="Calibri" w:cstheme="minorBidi"/><w:color w:val="000000" w:themeColor="text1"/><w:kern w:val="24"/><w:sz w:val="24"/><w:szCs w:val="24"/></w:rPr></w:pPr><w:r w:rsidRPr="00832718"><w:rPr><w:rFonts w:asciiTheme="minorHAnsi" w:hAnsi="Calibri" w:cstheme="minorBidi"/><w:color w:val="000000" w:themeColor="text1"/><w:kern w:val="24"/><w:sz w:val="24"/><w:szCs w:val="24"/></w:rPr><w:t>(</w:t></w:r><w:proofErr w:type="gramStart"/><w:r w:rsidRPr="00832718"><w:rPr><w:rFonts w:asciiTheme="minorHAnsi" w:hAnsi="Calibri" w:cstheme="minorBidi"/><w:color w:val="000000" w:themeColor="text1"/><w:kern w:val="24"/><w:sz w:val="24"/><w:szCs w:val="24"/></w:rPr><w:t>unhelpful</w:t></w:r><w:proofErr w:type="gramEnd"/><w:r w:rsidRPr="00832718"><w:rPr><w:rFonts w:asciiTheme="minorHAnsi" w:hAnsi="Calibri" w:cstheme="minorBidi"/><w:color w:val="000000" w:themeColor="text1"/><w:kern w:val="24"/><w:sz w:val="24"/><w:szCs w:val="24"/></w:rPr><w:t xml:space="preserve"> front desk) </w:t></w:r></w:p><w:p w14:paraId="3B1BC9BD" w14:textId="77777777" w:rsidR="00683359" w:rsidRDefault="00683359" w:rsidP="00681FA2"><w:pPr><w:pStyle w:val="NormalWeb"/><w:spacing w:before="0" w:beforeAutospacing="0" w:after="0" w:afterAutospacing="0"/><w:jc w:val="both"/><w:rPr><w:sz w:val="24"/><w:szCs w:val="24"/></w:rPr></w:pPr></w:p><w:p w14:paraId="34171F4B" w14:textId="77777777" w:rsidR="00683359" w:rsidRDefault="00683359" w:rsidP="00681FA2"><w:pPr><w:spacing w:after="0" w:line="240" w:lineRule="auto"/><w:jc w:val="both"/><w:rPr><w:sz w:val="24"/><w:szCs w:val="24"/></w:rPr></w:pPr></w:p><w:p w14:paraId="2A188B3E" w14:textId="4C3946F1" w:rsidR="00E814E3" w:rsidRPr="00A55ACE" w:rsidRDefault="00513D6B" w:rsidP="00E814E3"><w:pPr><w:jc w:val="both"/><w:rPr><w:rFonts w:ascii="Times" w:hAnsi="Times"/><w:b/><w:sz w:val="30"/><w:szCs w:val="30"/><w:u w:val="single"/></w:rPr></w:pPr><w:r><w:rPr><w:rFonts w:ascii="Times" w:hAnsi="Times"/><w:b/><w:sz w:val="30"/><w:szCs w:val="30"/><w:u w:val="single"/></w:rPr><w:t>Methods</w:t></w:r></w:p><w:p w14:paraId="2FDDB59C" w14:textId="3FDA6F23" w:rsidR="00F925FE" w:rsidRDefault="00E814E3" w:rsidP="00681FA2"><w:pPr><w:spacing w:after="0" w:line="240" w:lineRule="auto"/><w:jc w:val="both"/><w:rPr><w:sz w:val="24"/><w:szCs w:val="24"/></w:rPr></w:pPr><w:r><w:rPr><w:sz w:val="24"/><w:szCs w:val="24"/></w:rPr><w:t>To addres</w:t></w:r><w:r w:rsidR="009A0C34"><w:rPr><w:sz w:val="24"/><w:szCs w:val="24"/></w:rPr><w:t>s the project, we decided to use</w:t></w:r><w:r><w:rPr><w:sz w:val="24"/><w:szCs w:val="24"/></w:rPr><w:t xml:space="preserve"> </w:t></w:r><w:r w:rsidRPr="00E814E3"><w:rPr><w:sz w:val="24"/><w:szCs w:val="24"/></w:rPr><w:t>text mining and machine learning to extract useful information from text reviews, automatically categorize sentence into topics, and provide senti</w:t></w:r><w:r w:rsidR="00D87F3F"><w:rPr><w:sz w:val="24"/><w:szCs w:val="24"/></w:rPr><w:t>ment score of a certain review. The overall framework of our method is shown as below:</w:t></w:r></w:p><w:p w14:paraId="54C25F9A" w14:textId="77777777" w:rsidR="00D87F3F" w:rsidRDefault="00D87F3F" w:rsidP="00681FA2"><w:pPr><w:spacing w:after="0" w:line="240" w:lineRule="auto"/><w:jc w:val="both"/><w:rPr><w:sz w:val="24"/><w:szCs w:val="24"/></w:rPr></w:pPr></w:p><w:p w14:paraId="0AA29BCC" w14:textId="4B3C3976" w:rsidR="00E814E3" w:rsidRDefault="00BA2A17" w:rsidP="00681FA2"><w:pPr><w:spacing w:after="0" w:line="240" w:lineRule="auto"/><w:jc w:val="both"/><w:rPr><w:sz w:val="24"/><w:szCs w:val="24"/></w:rPr></w:pPr><w:r><w:rPr><w:noProof/><w:sz w:val="24"/><w:szCs w:val="24"/><w:lang w:eastAsia="en-US"/></w:rPr><w:drawing><wp:inline distT="0" distB="0" distL="0" distR="0" wp14:anchorId="57A256CC" wp14:editId="696BED01"><wp:extent cx="5930265" cy="2595245"/><wp:effectExtent l="0" t="0" r="0" b="0"/><wp:docPr id="1" name="Picture 1" descr="Macintosh HD:Users:YaxiongCai:Desktop:Screen Shot 2015-05-01 at 1.59.34 PM.png"/><wp:cNvGraphicFramePr><a:graphicFrameLocks xmlns:a="http://schemas.openxmlformats.org/drawingml/2006/main" noChangeAspect="1"/></wp:cNvGraphicFramePr><a:graphic xmlns:a="http://schemas.openxmlformats.org/drawingml/2006/main"><a:graphicData uri="http://schemas.openxmlformats.org/drawingml/2006/picture"><pic:pic xmlns:pic="http://schemas.openxmlformats.org/drawingml/2006/picture"><pic:nvPicPr><pic:cNvPr id="0" name="Picture 1" descr="Macintosh HD:Users:YaxiongCai:Desktop:Screen Shot 2015-05-01 at 1.59.34 PM.png"/><pic:cNvPicPr><a:picLocks noChangeAspect="1" noChangeArrowheads="1"/></pic:cNvPicPr></pic:nvPicPr><pic:blipFill><a:blip r:embed="rId6"><a:extLst><a:ext uri="{28A0092B-C50C-407E-A947-70E740481C1C}"><a14:useLocalDpi xmlns:a14="http://schemas.microsoft.com/office/drawing/2010/main" val="0"/></a:ext></a:extLst></a:blip><a:srcRect/><a:stretch><a:fillRect/></a:stretch></pic:blipFill><pic:spPr bwMode="auto"><a:xfrm><a:off x="0" y="0"/><a:ext cx="5930265" cy="2595245"/></a:xfrm><a:prstGeom prst="rect"><a:avLst/></a:prstGeom><a:noFill/><a:ln><a:noFill/></a:ln></pic:spPr></pic:pic></a:graphicData></a:graphic></wp:inline></w:drawing></w:r></w:p><w:p w14:paraId="1B3FA585" w14:textId="77777777" w:rsidR="00E814E3" w:rsidRDefault="00E814E3" w:rsidP="00681FA2"><w:pPr><w:spacing w:after="0" w:line="240" w:lineRule="auto"/><w:jc w:val="both"/><w:rPr><w:sz w:val="24"/><w:szCs w:val="24"/></w:rPr></w:pPr></w:p><w:p w14:paraId="76184C98" w14:textId="0EB2E493" w:rsidR="00683359" w:rsidRDefault="002B4A2C" w:rsidP="00681FA2"><w:pPr><w:spacing w:after="0" w:line="240" w:lineRule="auto"/><w:jc w:val="both"/><w:rPr><w:sz w:val="24"/><w:szCs w:val="24"/></w:rPr></w:pPr><w:r><w:rPr><w:sz w:val="24"/><w:szCs w:val="24"/></w:rPr><w:t>Then we</w:t></w:r><w:r w:rsidR="00683359"><w:rPr><w:sz w:val="24"/><w:szCs w:val="24"/></w:rPr><w:t xml:space="preserve"> proposed steps for constructing this system are as follows</w:t></w:r><w:r w:rsidR="00683359" w:rsidRPr="003341D4"><w:rPr><w:sz w:val="24"/><w:szCs w:val="24"/></w:rPr><w:t>:</w:t></w:r></w:p><w:p w14:paraId="64D1543F" w14:textId="77777777" w:rsidR="002C74C1" w:rsidRPr="003341D4" w:rsidRDefault="002C74C1" w:rsidP="00681FA2"><w:pPr><w:spacing w:after="0" w:line="240" w:lineRule="auto"/><w:jc w:val="both"/><w:rPr><w:sz w:val="24"/><w:szCs w:val="24"/></w:rPr></w:pPr></w:p><w:p w14:paraId="1D3F66F2" w14:textId="08FBA4CD" w:rsidR="00683359" w:rsidRDefault="00683359" w:rsidP="00681FA2"><w:pPr><w:numPr><w:ilvl w:val="0"/><w:numId w:val="1"/></w:numPr><w:tabs><w:tab w:val="clear" w:pos="720"/><w:tab w:val="num" w:pos="0"/><w:tab w:val="left" w:pos="270"/></w:tabs><w:spacing w:after="0" w:line="240" w:lineRule="auto"/><w:ind w:left="180" w:hanging="180"/><w:jc w:val="both"/><w:rPr><w:b/><w:sz w:val="24"/><w:szCs w:val="24"/></w:rPr></w:pPr><w:r w:rsidRPr="00223EBC"><w:rPr><w:b/><w:sz w:val="24"/><w:szCs w:val="24"/></w:rPr><w:t>Text cleaning of free-form responses</w:t></w:r><w:r w:rsidR="00591DD0"><w:rPr><w:b/><w:sz w:val="24"/><w:szCs w:val="24"/></w:rPr><w:t xml:space="preserve"> </w:t></w:r><w:r w:rsidR="00591DD0" w:rsidRPr="00591DD0"><w:rPr><w:sz w:val="24"/><w:szCs w:val="24"/><w:highlight w:val="yellow"/></w:rPr><w:t>AS</w:t></w:r></w:p><w:p w14:paraId="4D99EFB2" w14:textId="77777777" w:rsidR="002C74C1" w:rsidRPr="00223EBC" w:rsidRDefault="002C74C1" w:rsidP="002C74C1"><w:pPr><w:tabs><w:tab w:val="left" w:pos="270"/></w:tabs><w:spacing w:after="0" w:line="240" w:lineRule="auto"/><w:ind w:left="180"/><w:jc w:val="both"/><w:rPr><w:b/><w:sz w:val="24"/><w:szCs w:val="24"/></w:rPr></w:pPr></w:p><w:p w14:paraId="245D11FB" w14:textId="77777777" w:rsidR="00683359" w:rsidRDefault="00683359" w:rsidP="00681FA2"><w:pPr><w:tabs><w:tab w:val="num" w:pos="0"/></w:tabs><w:spacing w:after="0" w:line="240" w:lineRule="auto"/><w:ind w:left="180" w:hanging="180"/><w:jc w:val="both"/><w:rPr><w:sz w:val="24"/><w:szCs w:val="24"/></w:rPr></w:pPr><w:r><w:rPr><w:sz w:val="24"/><w:szCs w:val="24"/></w:rPr><w:tab/><w:t>This process includes grammar and spell checking, in addition to the removal of unrecognizable characters. Then each review is split into individual sentences and tokenized using built-in functions, such as those available through NLTK.</w:t></w:r></w:p><w:p w14:paraId="21878947" w14:textId="0BCE8215" w:rsidR="00683359" w:rsidRDefault="00995AD9" w:rsidP="00681FA2"><w:pPr><w:numPr><w:ilvl w:val="0"/><w:numId w:val="1"/></w:numPr><w:tabs><w:tab w:val="clear" w:pos="720"/><w:tab w:val="num" w:pos="0"/><w:tab w:val="left" w:pos="270"/></w:tabs><w:spacing w:after="0" w:line="240" w:lineRule="auto"/><w:ind w:left="180" w:hanging="180"/><w:jc w:val="both"/><w:rPr><w:b/><w:sz w:val="24"/><w:szCs w:val="24"/></w:rPr></w:pPr><w:r><w:rPr><w:b/><w:sz w:val="24"/><w:szCs w:val="24"/></w:rPr><w:t xml:space="preserve">Map each sentence to </w:t></w:r><w:r w:rsidR="002C74C1"><w:rPr><w:b/><w:sz w:val="24"/><w:szCs w:val="24"/></w:rPr><w:t>categories using classification</w:t></w:r></w:p><w:p w14:paraId="39032ECE" w14:textId="77777777" w:rsidR="002C74C1" w:rsidRDefault="002C74C1" w:rsidP="002C74C1"><w:pPr><w:tabs><w:tab w:val="left" w:pos="270"/></w:tabs><w:spacing w:after="0" w:line="240" w:lineRule="auto"/><w:ind w:left="180"/><w:jc w:val="both"/><w:rPr><w:b/><w:sz w:val="24"/><w:szCs w:val="24"/></w:rPr></w:pPr></w:p><w:p w14:paraId="3FD2E461" w14:textId="0C611C06" w:rsidR="00995AD9" w:rsidRDefault="00995AD9" w:rsidP="00E73206"><w:pPr><w:pStyle w:val="ListParagraph"/><w:numPr><w:ilvl w:val="0"/><w:numId w:val="3"/></w:numPr><w:tabs><w:tab w:val="left" w:pos="270"/></w:tabs><w:spacing w:after="0" w:line="240" w:lineRule="auto"/><w:jc w:val="both"/><w:rPr><w:i/><w:sz w:val="24"/><w:szCs w:val="24"/></w:rPr></w:pPr><w:r w:rsidRPr="00995AD9"><w:rPr><w:i/><w:sz w:val="24"/><w:szCs w:val="24"/></w:rPr><w:t>Matrix Construction</w:t></w:r><w:r w:rsidR="00B34177"><w:rPr><w:i/><w:sz w:val="24"/><w:szCs w:val="24"/></w:rPr><w:t xml:space="preserve"> for training data</w:t></w:r><w:r w:rsidRPr="00995AD9"><w:rPr><w:i/><w:sz w:val="24"/><w:szCs w:val="24"/></w:rPr><w:t>:</w:t></w:r><w:r w:rsidR="00591DD0"><w:rPr><w:i/><w:sz w:val="24"/><w:szCs w:val="24"/></w:rPr><w:t xml:space="preserve"> </w:t></w:r><w:r w:rsidR="00591DD0" w:rsidRPr="00591DD0"><w:rPr><w:i/><w:sz w:val="24"/><w:szCs w:val="24"/><w:highlight w:val="yellow"/></w:rPr><w:t>JC</w:t></w:r></w:p><w:p w14:paraId="1B32257C" w14:textId="77777777" w:rsidR="007022BB" w:rsidRPr="007022BB" w:rsidRDefault="007022BB" w:rsidP="007022BB"><w:pPr><w:pStyle w:val="ListParagraph"/><w:tabs><w:tab w:val="left" w:pos="270"/></w:tabs><w:spacing w:after="0" w:line="240" w:lineRule="auto"/><w:ind w:left="540"/><w:jc w:val="both"/><w:rPr><w:sz w:val="24"/><w:szCs w:val="24"/></w:rPr></w:pPr></w:p><w:p w14:paraId="5541AEDE" w14:textId="7D226284" w:rsidR="00995AD9" w:rsidRDefault="00533590" w:rsidP="00995AD9"><w:pPr><w:pStyle w:val="ListParagraph"/><w:tabs><w:tab w:val="left" w:pos="270"/></w:tabs><w:spacing w:after="0" w:line="240" w:lineRule="auto"/><w:ind w:left="540"/><w:jc w:val="both"/><w:rPr><w:sz w:val="24"/><w:szCs w:val="24"/></w:rPr></w:pPr><w:r><w:rPr><w:sz w:val="24"/><w:szCs w:val="24"/></w:rPr><w:t xml:space="preserve">In order to do classification from sentence to topics, we firstly have to transfer each sentence into a binary vector. To achieve this, we </w:t></w:r><w:r w:rsidR="00B34177"><w:rPr><w:sz w:val="24"/><w:szCs w:val="24"/></w:rPr><w:t xml:space="preserve">firstly </w:t></w:r><w:r><w:rPr><w:sz w:val="24"/><w:szCs w:val="24"/></w:rPr><w:t xml:space="preserve">create a dictionary </w:t></w:r><w:r w:rsidR="00B34177"><w:rPr><w:sz w:val="24"/><w:szCs w:val="24"/></w:rPr><w:t>that contains all unique words. T</w:t></w:r><w:r><w:rPr><w:sz w:val="24"/><w:szCs w:val="24"/></w:rPr><w:t>hen</w:t></w:r><w:r w:rsidR="00B34177"><w:rPr><w:sz w:val="24"/><w:szCs w:val="24"/></w:rPr><w:t xml:space="preserve"> we</w:t></w:r><w:r><w:rPr><w:sz w:val="24"/><w:szCs w:val="24"/></w:rPr><w:t xml:space="preserve"> construct a matrix1 that has the number of rows as number of sentences and number of columns as number of all unique words. </w:t></w:r><w:r w:rsidR="00B34177"><w:rPr><w:sz w:val="24"/><w:szCs w:val="24"/></w:rPr><w:t>E</w:t></w:r><w:r w:rsidR="007022BB"><w:rPr><w:sz w:val="24"/><w:szCs w:val="24"/></w:rPr><w:t>ach input sentence</w:t></w:r><w:r w:rsidR="00B34177"><w:rPr><w:sz w:val="24"/><w:szCs w:val="24"/></w:rPr><w:t xml:space="preserve"> is associated with one row in the matrix1. If a word appears, we denoted the corresponding place 1, otherwise 0. Hence we can construct all sentences into the binary matrix1.</w:t></w:r></w:p><w:p w14:paraId="484E410D" w14:textId="77777777" w:rsidR="00B34177" w:rsidRDefault="00B34177" w:rsidP="00995AD9"><w:pPr><w:pStyle w:val="ListParagraph"/><w:tabs><w:tab w:val="left" w:pos="270"/></w:tabs><w:spacing w:after="0" w:line="240" w:lineRule="auto"/><w:ind w:left="540"/><w:jc w:val="both"/><w:rPr><w:sz w:val="24"/><w:szCs w:val="24"/></w:rPr></w:pPr></w:p><w:p w14:paraId="2B2A5724" w14:textId="6B734A39" w:rsidR="00B34177" w:rsidRDefault="00B34177" w:rsidP="00995AD9"><w:pPr><w:pStyle w:val="ListParagraph"/><w:tabs><w:tab w:val="left" w:pos="270"/></w:tabs><w:spacing w:after="0" w:line="240" w:lineRule="auto"/><w:ind w:left="540"/><w:jc w:val="both"/><w:rPr><w:sz w:val="24"/><w:szCs w:val="24"/></w:rPr></w:pPr><w:r><w:rPr><w:sz w:val="24"/><w:szCs w:val="24"/></w:rPr><w:t>On the other hand, we also construct a matrix2 that has the number of rows as number of sentences and number of columns as number of categories.</w:t></w:r><w:r w:rsidR="002A6635"><w:rPr><w:sz w:val="24"/><w:szCs w:val="24"/></w:rPr><w:t xml:space="preserve"> And if a sentence belongs to a certain category, we denoted that place ‘1’, other wise 0.</w:t></w:r><w:r><w:rPr><w:sz w:val="24"/><w:szCs w:val="24"/></w:rPr><w:t xml:space="preserve"> </w:t></w:r><w:r w:rsidR="002A6635"><w:rPr><w:sz w:val="24"/><w:szCs w:val="24"/></w:rPr><w:t>In</w:t></w:r><w:r w:rsidR="009B57D3"><w:rPr><w:sz w:val="24"/><w:szCs w:val="24"/></w:rPr><w:t xml:space="preserve"> this way, each column of matrix2 represents a category of all sentences. </w:t></w:r><w:r w:rsidR="00B35CDE"><w:rPr><w:sz w:val="24"/><w:szCs w:val="24"/></w:rPr><w:t xml:space="preserve">Each row of matrix2 represents the </w:t></w:r><w:r w:rsidR="005800C5"><w:rPr><w:sz w:val="24"/><w:szCs w:val="24"/></w:rPr><w:t>topic(s) associated with that sentence.</w:t></w:r></w:p><w:p w14:paraId="2F85DC21" w14:textId="77777777" w:rsidR="00995AD9" w:rsidRDefault="00995AD9" w:rsidP="00995AD9"><w:pPr><w:pStyle w:val="ListParagraph"/><w:tabs><w:tab w:val="left" w:pos="270"/></w:tabs><w:spacing w:after="0" w:line="240" w:lineRule="auto"/><w:ind w:left="540"/><w:jc w:val="both"/><w:rPr><w:sz w:val="24"/><w:szCs w:val="24"/></w:rPr></w:pPr></w:p><w:p w14:paraId="59FDCC33" w14:textId="3C090D84" w:rsidR="00995AD9" w:rsidRDefault="00F4779D" w:rsidP="007B300E"><w:pPr><w:pStyle w:val="ListParagraph"/><w:tabs><w:tab w:val="left" w:pos="270"/></w:tabs><w:spacing w:after="0" w:line="240" w:lineRule="auto"/><w:ind w:left="540"/><w:jc w:val="both"/><w:rPr><w:sz w:val="24"/><w:szCs w:val="24"/></w:rPr></w:pPr><w:r><w:rPr><w:sz w:val="24"/><w:szCs w:val="24"/></w:rPr><w:t>We train all sentences in matrix1 with every column of matrix2. In this way, this forms a number of categories classifiers. Then we pass in a new sentence or adjective/ noun pair into each of the classifier to do prediction.</w:t></w:r></w:p><w:p w14:paraId="4258638F" w14:textId="77777777" w:rsidR="007B300E" w:rsidRPr="007B300E" w:rsidRDefault="007B300E" w:rsidP="007B300E"><w:pPr><w:pStyle w:val="ListParagraph"/><w:tabs><w:tab w:val="left" w:pos="270"/></w:tabs><w:spacing w:after="0" w:line="240" w:lineRule="auto"/><w:ind w:left="540"/><w:jc w:val="both"/><w:rPr><w:sz w:val="24"/><w:szCs w:val="24"/></w:rPr></w:pPr></w:p><w:p w14:paraId="6018B934" w14:textId="77777777" w:rsidR="00995AD9" w:rsidRPr="00995AD9" w:rsidRDefault="00995AD9" w:rsidP="00995AD9"><w:pPr><w:pStyle w:val="ListParagraph"/><w:tabs><w:tab w:val="left" w:pos="270"/></w:tabs><w:spacing w:after="0" w:line="240" w:lineRule="auto"/><w:ind w:left="540"/><w:jc w:val="both"/><w:rPr><w:sz w:val="24"/><w:szCs w:val="24"/></w:rPr></w:pPr></w:p><w:p w14:paraId="4D73243A" w14:textId="3EB36C2C" w:rsidR="00995AD9" w:rsidRPr="00995AD9" w:rsidRDefault="00995AD9" w:rsidP="00E73206"><w:pPr><w:pStyle w:val="ListParagraph"/><w:numPr><w:ilvl w:val="0"/><w:numId w:val="3"/></w:numPr><w:tabs><w:tab w:val="left" w:pos="270"/></w:tabs><w:spacing w:after="0" w:line="240" w:lineRule="auto"/><w:jc w:val="both"/><w:rPr><w:i/><w:sz w:val="24"/><w:szCs w:val="24"/></w:rPr></w:pPr><w:r><w:rPr><w:i/><w:sz w:val="24"/><w:szCs w:val="24"/></w:rPr><w:t>Random Forest Classification</w:t></w:r><w:r w:rsidR="00591DD0"><w:rPr><w:i/><w:sz w:val="24"/><w:szCs w:val="24"/></w:rPr><w:t xml:space="preserve"> </w:t></w:r><w:r w:rsidR="00591DD0" w:rsidRPr="00591DD0"><w:rPr><w:i/><w:sz w:val="24"/><w:szCs w:val="24"/><w:highlight w:val="yellow"/></w:rPr><w:t>JC</w:t></w:r></w:p><w:p w14:paraId="7069E2C1" w14:textId="77777777" w:rsidR="00995AD9" w:rsidRPr="0069348C" w:rsidRDefault="00995AD9" w:rsidP="00995AD9"><w:pPr><w:pStyle w:val="ListParagraph"/><w:tabs><w:tab w:val="left" w:pos="270"/></w:tabs><w:spacing w:after="0" w:line="240" w:lineRule="auto"/><w:ind w:left="540"/><w:jc w:val="both"/><w:rPr><w:sz w:val="24"/><w:szCs w:val="24"/></w:rPr></w:pPr></w:p><w:p w14:paraId="12D7573F" w14:textId="0C5C3B0C" w:rsidR="00402445" w:rsidRPr="00EF2785" w:rsidRDefault="0069348C" w:rsidP="00EF2785"><w:pPr><w:pStyle w:val="ListParagraph"/><w:tabs><w:tab w:val="left" w:pos="270"/></w:tabs><w:spacing w:after="0" w:line="240" w:lineRule="auto"/><w:ind w:left="540"/><w:jc w:val="both"/><w:rPr><w:sz w:val="24"/><w:szCs w:val="24"/></w:rPr></w:pPr><w:r w:rsidRPr="0069348C"><w:rPr><w:sz w:val="24"/><w:szCs w:val="24"/></w:rPr><w:t>Random forests are an ensemble learning method for classification, regression and other tasks, that operate by constructing a multitude of decision trees at training time and outputting the class that is the mode of the classes (classification) or mean prediction (regression) of the individual trees.</w:t></w:r><w:r><w:rPr><w:sz w:val="24"/><w:szCs w:val="24"/></w:rPr><w:t xml:space="preserve"> In our cases, we pass in many rows in matrix1 with their corresponding topics in matrix2 as training set, and then use random forest to in python library </w:t></w:r><w:proofErr w:type="spellStart"/><w:r><w:rPr><w:sz w:val="24"/><w:szCs w:val="24"/></w:rPr><w:t>sk</w:t></w:r><w:proofErr w:type="spellEnd"/><w:r><w:rPr><w:sz w:val="24"/><w:szCs w:val="24"/></w:rPr><w:t>-learn to train them. The training information is contained in “</w:t></w:r><w:proofErr w:type="spellStart"/><w:r><w:rPr><w:sz w:val="24"/><w:szCs w:val="24"/></w:rPr><w:t>clf</w:t></w:r><w:proofErr w:type="spellEnd"/><w:r><w:rPr><w:sz w:val="24"/><w:szCs w:val="24"/></w:rPr><w:t xml:space="preserve"> “. After that, we use “</w:t></w:r><w:proofErr w:type="spellStart"/><w:r><w:rPr><w:sz w:val="24"/><w:szCs w:val="24"/></w:rPr><w:t>clf</w:t></w:r><w:proofErr w:type="spellEnd"/><w:r><w:rPr><w:sz w:val="24"/><w:szCs w:val="24"/></w:rPr><w:t>” to predict new imported sentence.</w:t></w:r></w:p><w:p w14:paraId="3A6FF5D7" w14:textId="77777777" w:rsidR="0069348C" w:rsidRPr="0069348C" w:rsidRDefault="0069348C" w:rsidP="00995AD9"><w:pPr><w:pStyle w:val="ListParagraph"/><w:tabs><w:tab w:val="left" w:pos="270"/></w:tabs><w:spacing w:after="0" w:line="240" w:lineRule="auto"/><w:ind w:left="540"/><w:jc w:val="both"/><w:rPr><w:sz w:val="24"/><w:szCs w:val="24"/></w:rPr></w:pPr></w:p><w:p w14:paraId="45DE4D10" w14:textId="5734BEBF" w:rsidR="00072560" w:rsidRDefault="00072560" w:rsidP="00995AD9"><w:pPr><w:pStyle w:val="ListParagraph"/><w:tabs><w:tab w:val="left" w:pos="270"/></w:tabs><w:spacing w:after="0" w:line="240" w:lineRule="auto"/><w:ind w:left="540"/><w:jc w:val="both"/><w:rPr><w:sz w:val="24"/><w:szCs w:val="24"/></w:rPr></w:pPr><w:r w:rsidRPr="0069348C"><w:rPr><w:sz w:val="24"/><w:szCs w:val="24"/></w:rPr><w:t>Here</w:t></w:r><w:r><w:rPr><w:sz w:val="24"/><w:szCs w:val="24"/></w:rPr><w:t xml:space="preserve"> we choose to use 10 folder cross validation to check our result. The plotting of the 10 folder cross validation with different number of trees is shown as below:</w:t></w:r></w:p><w:p w14:paraId="036FE650" w14:textId="77777777" w:rsidR="00D452BD" w:rsidRDefault="00D452BD" w:rsidP="00995AD9"><w:pPr><w:pStyle w:val="ListParagraph"/><w:tabs><w:tab w:val="left" w:pos="270"/></w:tabs><w:spacing w:after="0" w:line="240" w:lineRule="auto"/><w:ind w:left="540"/><w:jc w:val="both"/><w:rPr><w:color w:val="FF0000"/><w:sz w:val="24"/><w:szCs w:val="24"/></w:rPr></w:pPr></w:p><w:p w14:paraId="242FC211" w14:textId="44510C56" w:rsidR="00072560" w:rsidRPr="008533C7" w:rsidRDefault="00072560" w:rsidP="00995AD9"><w:pPr><w:pStyle w:val="ListParagraph"/><w:tabs><w:tab w:val="left" w:pos="270"/></w:tabs><w:spacing w:after="0" w:line="240" w:lineRule="auto"/><w:ind w:left="540"/><w:jc w:val="both"/><w:rPr><w:sz w:val="24"/><w:szCs w:val="24"/></w:rPr></w:pPr><w:r w:rsidRPr="00706074"><w:rPr><w:color w:val="FF0000"/><w:sz w:val="24"/><w:szCs w:val="24"/></w:rPr><w:t>TODO</w:t></w:r><w:r w:rsidR="00706074" w:rsidRPr="00706074"><w:rPr><w:color w:val="FF0000"/><w:sz w:val="24"/><w:szCs w:val="24"/></w:rPr><w:t xml:space="preserve">: </w:t></w:r><w:r w:rsidR="008533C7"><w:rPr><w:sz w:val="24"/><w:szCs w:val="24"/></w:rPr><w:t>T</w:t></w:r><w:r w:rsidR="00706074" w:rsidRPr="008533C7"><w:rPr><w:sz w:val="24"/><w:szCs w:val="24"/></w:rPr><w:t>ree</w:t></w:r><w:r w:rsidR="008533C7"><w:rPr><w:sz w:val="24"/><w:szCs w:val="24"/></w:rPr><w:t xml:space="preserve"> plot</w:t></w:r><w:bookmarkStart w:id="0" w:name="_GoBack"/><w:bookmarkEnd w:id="0"/></w:p><w:p w14:paraId="2D0E3835" w14:textId="1B2AAB2D" w:rsidR="00995AD9" w:rsidRPr="008533C7" w:rsidRDefault="00706074" w:rsidP="00995AD9"><w:pPr><w:pStyle w:val="ListParagraph"/><w:tabs><w:tab w:val="left" w:pos="270"/></w:tabs><w:spacing w:after="0" w:line="240" w:lineRule="auto"/><w:ind w:left="540"/><w:jc w:val="both"/><w:rPr><w:sz w:val="24"/><w:szCs w:val="24"/></w:rPr></w:pPr><w:r w:rsidRPr="00706074"><w:rPr><w:color w:val="FF0000"/><w:sz w:val="24"/><w:szCs w:val="24"/></w:rPr><w:t xml:space="preserve">TODO: </w:t></w:r><w:r w:rsidRPr="008533C7"><w:rPr><w:sz w:val="24"/><w:szCs w:val="24"/></w:rPr><w:t>Analysis of number of trees</w:t></w:r></w:p><w:p w14:paraId="4C97BC8F" w14:textId="77777777" w:rsidR="00072560" w:rsidRDefault="00072560" w:rsidP="00995AD9"><w:pPr><w:pStyle w:val="ListParagraph"/><w:tabs><w:tab w:val="left" w:pos="270"/></w:tabs><w:spacing w:after="0" w:line="240" w:lineRule="auto"/><w:ind w:left="540"/><w:jc w:val="both"/><w:rPr><w:sz w:val="24"/><w:szCs w:val="24"/></w:rPr></w:pPr></w:p><w:p w14:paraId="144AB831" w14:textId="4914C73B" w:rsidR="00D452BD" w:rsidRPr="00D452BD" w:rsidRDefault="00D452BD" w:rsidP="00D452BD"><w:pPr><w:pStyle w:val="ListParagraph"/><w:tabs><w:tab w:val="left" w:pos="270"/></w:tabs><w:spacing w:after="0" w:line="240" w:lineRule="auto"/><w:ind w:left="540"/><w:jc w:val="both"/><w:rPr><w:sz w:val="24"/><w:szCs w:val="24"/></w:rPr></w:pPr><w:r><w:rPr><w:sz w:val="24"/><w:szCs w:val="24"/></w:rPr><w:t xml:space="preserve">In addition, </w:t></w:r><w:r w:rsidRPr="00D452BD"><w:rPr><w:sz w:val="24"/><w:szCs w:val="24"/></w:rPr><w:t>Random Forest Classification</w:t></w:r><w:r><w:rPr><w:sz w:val="24"/><w:szCs w:val="24"/></w:rPr><w:t xml:space="preserve"> gives us the information about the importance of feature</w:t></w:r><w:r w:rsidR="00295DD5"><w:rPr><w:sz w:val="24"/><w:szCs w:val="24"/></w:rPr><w:t>s in each classifier</w:t></w:r><w:r><w:rPr><w:sz w:val="24"/><w:szCs w:val="24"/></w:rPr><w:t xml:space="preserve">. </w:t></w:r><w:r w:rsidR="00295DD5"><w:rPr><w:sz w:val="24"/><w:szCs w:val="24"/></w:rPr><w:t>Here we included the instance of “</w:t></w:r><w:r w:rsidR="00295DD5" w:rsidRPr="00295DD5"><w:rPr><w:color w:val="FF0000"/><w:sz w:val="24"/><w:szCs w:val="24"/></w:rPr><w:t>??</w:t></w:r><w:proofErr w:type="gramStart"/><w:r w:rsidR="00295DD5"><w:rPr><w:sz w:val="24"/><w:szCs w:val="24"/></w:rPr><w:t>”</w:t></w:r><w:r w:rsidR="00CA08DA"><w:rPr><w:sz w:val="24"/><w:szCs w:val="24"/></w:rPr><w:t>.</w:t></w:r><w:proofErr w:type="gramEnd"/><w:r w:rsidR="00CA08DA"><w:rPr><w:sz w:val="24"/><w:szCs w:val="24"/></w:rPr><w:t xml:space="preserve"> Plot of importance of features </w:t></w:r><w:proofErr w:type="gramStart"/><w:r w:rsidR="00CA08DA"><w:rPr><w:sz w:val="24"/><w:szCs w:val="24"/></w:rPr><w:t xml:space="preserve">of </w:t></w:r><w:r w:rsidR="00CA08DA" w:rsidRPr="00CA08DA"><w:rPr><w:color w:val="FF0000"/><w:sz w:val="24"/><w:szCs w:val="24"/></w:rPr><w:t>?</w:t></w:r><w:proofErr w:type="gramEnd"/><w:r w:rsidR="00CA08DA" w:rsidRPr="00CA08DA"><w:rPr><w:color w:val="FF0000"/><w:sz w:val="24"/><w:szCs w:val="24"/></w:rPr><w:t>?</w:t></w:r><w:r w:rsidR="00CA08DA"><w:rPr><w:sz w:val="24"/><w:szCs w:val="24"/></w:rPr><w:t xml:space="preserve"> </w:t></w:r><w:proofErr w:type="gramStart"/><w:r w:rsidR="00CA08DA"><w:rPr><w:sz w:val="24"/><w:szCs w:val="24"/></w:rPr><w:t>is</w:t></w:r><w:proofErr w:type="gramEnd"/><w:r w:rsidR="00CA08DA"><w:rPr><w:sz w:val="24"/><w:szCs w:val="24"/></w:rPr><w:t xml:space="preserve"> shown as below:</w:t></w:r></w:p><w:p w14:paraId="7429A1A6" w14:textId="27B34577" w:rsidR="00072560" w:rsidRDefault="00CA08DA" w:rsidP="00995AD9"><w:pPr><w:pStyle w:val="ListParagraph"/><w:tabs><w:tab w:val="left" w:pos="270"/></w:tabs><w:spacing w:after="0" w:line="240" w:lineRule="auto"/><w:ind w:left="540"/><w:jc w:val="both"/><w:rPr><w:sz w:val="24"/><w:szCs w:val="24"/></w:rPr></w:pPr><w:r w:rsidRPr="00964C6A"><w:rPr><w:color w:val="FF0000"/><w:sz w:val="24"/><w:szCs w:val="24"/></w:rPr><w:t>TODO</w:t></w:r><w:r><w:rPr><w:sz w:val="24"/><w:szCs w:val="24"/></w:rPr><w:t>: feature plot</w:t></w:r></w:p><w:p w14:paraId="497AE899" w14:textId="0092DD75" w:rsidR="00964C6A" w:rsidRDefault="00577C65" w:rsidP="00995AD9"><w:pPr><w:pStyle w:val="ListParagraph"/><w:tabs><w:tab w:val="left" w:pos="270"/></w:tabs><w:spacing w:after="0" w:line="240" w:lineRule="auto"/><w:ind w:left="540"/><w:jc w:val="both"/><w:rPr><w:sz w:val="24"/><w:szCs w:val="24"/></w:rPr></w:pPr><w:r w:rsidRPr="00964C6A"><w:rPr><w:color w:val="FF0000"/><w:sz w:val="24"/><w:szCs w:val="24"/></w:rPr><w:t>TODO</w:t></w:r><w:r><w:rPr><w:color w:val="FF0000"/><w:sz w:val="24"/><w:szCs w:val="24"/></w:rPr><w:t xml:space="preserve">: </w:t></w:r><w:r w:rsidRPr="00577C65"><w:rPr><w:sz w:val="24"/><w:szCs w:val="24"/></w:rPr><w:t>Analysis</w:t></w:r></w:p><w:p w14:paraId="1D468941" w14:textId="77777777" w:rsidR="00577C65" w:rsidRDefault="00577C65" w:rsidP="00995AD9"><w:pPr><w:pStyle w:val="ListParagraph"/><w:tabs><w:tab w:val="left" w:pos="270"/></w:tabs><w:spacing w:after="0" w:line="240" w:lineRule="auto"/><w:ind w:left="540"/><w:jc w:val="both"/><w:rPr><w:sz w:val="24"/><w:szCs w:val="24"/></w:rPr></w:pPr></w:p><w:p w14:paraId="360C3B7C" w14:textId="3090DE24" w:rsidR="00577C65" w:rsidRPr="00577C65" w:rsidRDefault="00577C65" w:rsidP="00995AD9"><w:pPr><w:pStyle w:val="ListParagraph"/><w:tabs><w:tab w:val="left" w:pos="270"/></w:tabs><w:spacing w:after="0" w:line="240" w:lineRule="auto"/><w:ind w:left="540"/><w:jc w:val="both"/><w:rPr><w:sz w:val="24"/><w:szCs w:val="24"/></w:rPr></w:pPr><w:r><w:rPr><w:sz w:val="24"/><w:szCs w:val="24"/></w:rPr><w:t>This plot actually gives us essential insights about how we have further improved our classification result. The detail of the improvement is included in the part4 “further improvements”.</w:t></w:r></w:p><w:p w14:paraId="4EF5A0C8" w14:textId="77777777" w:rsidR="00706074" w:rsidRDefault="00706074" w:rsidP="00995AD9"><w:pPr><w:pStyle w:val="ListParagraph"/><w:tabs><w:tab w:val="left" w:pos="270"/></w:tabs><w:spacing w:after="0" w:line="240" w:lineRule="auto"/><w:ind w:left="540"/><w:jc w:val="both"/><w:rPr><w:sz w:val="24"/><w:szCs w:val="24"/></w:rPr></w:pPr></w:p><w:p w14:paraId="40A6C9CB" w14:textId="77777777" w:rsidR="00577C65" w:rsidRPr="00072560" w:rsidRDefault="00577C65" w:rsidP="00995AD9"><w:pPr><w:pStyle w:val="ListParagraph"/><w:tabs><w:tab w:val="left" w:pos="270"/></w:tabs><w:spacing w:after="0" w:line="240" w:lineRule="auto"/><w:ind w:left="540"/><w:jc w:val="both"/><w:rPr><w:sz w:val="24"/><w:szCs w:val="24"/></w:rPr></w:pPr></w:p><w:p w14:paraId="158F2053" w14:textId="18A9F452" w:rsidR="00995AD9" w:rsidRDefault="00995AD9" w:rsidP="00E73206"><w:pPr><w:pStyle w:val="ListParagraph"/><w:numPr><w:ilvl w:val="0"/><w:numId w:val="3"/></w:numPr><w:tabs><w:tab w:val="left" w:pos="270"/></w:tabs><w:spacing w:after="0" w:line="240" w:lineRule="auto"/><w:jc w:val="both"/><w:rPr><w:sz w:val="24"/><w:szCs w:val="24"/></w:rPr></w:pPr><w:r w:rsidRPr="00995AD9"><w:rPr><w:sz w:val="24"/><w:szCs w:val="24"/></w:rPr><w:t>Logistic Regression</w:t></w:r><w:r w:rsidR="00591DD0"><w:rPr><w:sz w:val="24"/><w:szCs w:val="24"/></w:rPr><w:t xml:space="preserve"> </w:t></w:r><w:r w:rsidR="00591DD0" w:rsidRPr="00591DD0"><w:rPr><w:i/><w:sz w:val="24"/><w:szCs w:val="24"/><w:highlight w:val="yellow"/></w:rPr><w:t>JC</w:t></w:r></w:p><w:p w14:paraId="28241391" w14:textId="77777777" w:rsidR="00995AD9" w:rsidRDefault="00995AD9" w:rsidP="00995AD9"><w:pPr><w:pStyle w:val="ListParagraph"/><w:tabs><w:tab w:val="left" w:pos="270"/></w:tabs><w:spacing w:after="0" w:line="240" w:lineRule="auto"/><w:ind w:left="540"/><w:jc w:val="both"/><w:rPr><w:sz w:val="24"/><w:szCs w:val="24"/></w:rPr></w:pPr></w:p><w:p w14:paraId="377E0420" w14:textId="44FA4A3D" w:rsidR="000E4A1E" w:rsidRDefault="000E4A1E" w:rsidP="000E4A1E"><w:pPr><w:pStyle w:val="ListParagraph"/><w:tabs><w:tab w:val="left" w:pos="270"/></w:tabs><w:spacing w:after="0" w:line="240" w:lineRule="auto"/><w:ind w:left="540"/><w:jc w:val="both"/><w:rPr><w:sz w:val="24"/><w:szCs w:val="24"/></w:rPr></w:pPr><w:r w:rsidRPr="00072560"><w:rPr><w:color w:val="FF0000"/><w:sz w:val="24"/><w:szCs w:val="24"/></w:rPr><w:t>TODO</w:t></w:r><w:r w:rsidRPr="00072560"><w:rPr><w:sz w:val="24"/><w:szCs w:val="24"/></w:rPr><w:t>:</w:t></w:r><w:r><w:rPr><w:sz w:val="24"/><w:szCs w:val="24"/></w:rPr><w:t xml:space="preserve"> Concept of Logistics</w:t></w:r></w:p><w:p w14:paraId="6D99EBDC" w14:textId="77777777" w:rsidR="000E4A1E" w:rsidRDefault="000E4A1E" w:rsidP="000E4A1E"><w:pPr><w:pStyle w:val="ListParagraph"/><w:tabs><w:tab w:val="left" w:pos="270"/></w:tabs><w:spacing w:after="0" w:line="240" w:lineRule="auto"/><w:ind w:left="540"/><w:jc w:val="both"/><w:rPr><w:sz w:val="24"/><w:szCs w:val="24"/></w:rPr></w:pPr></w:p><w:p w14:paraId="78710BE6" w14:textId="1FC3D740" w:rsidR="000E4A1E" w:rsidRDefault="000E4A1E" w:rsidP="000E4A1E"><w:pPr><w:pStyle w:val="ListParagraph"/><w:tabs><w:tab w:val="left" w:pos="270"/></w:tabs><w:spacing w:after="0" w:line="240" w:lineRule="auto"/><w:ind w:left="540"/><w:jc w:val="both"/><w:rPr><w:sz w:val="24"/><w:szCs w:val="24"/></w:rPr></w:pPr><w:r><w:rPr><w:sz w:val="24"/><w:szCs w:val="24"/></w:rPr><w:t>Same as</w:t></w:r><w:r w:rsidR="00812CFE"><w:rPr><w:sz w:val="24"/><w:szCs w:val="24"/></w:rPr><w:t xml:space="preserve"> random forest,</w:t></w:r><w:r><w:rPr><w:sz w:val="24"/><w:szCs w:val="24"/></w:rPr><w:t xml:space="preserve"> we</w:t></w:r><w:r w:rsidR="00812CFE"><w:rPr><w:sz w:val="24"/><w:szCs w:val="24"/></w:rPr><w:t xml:space="preserve"> also</w:t></w:r><w:r><w:rPr><w:sz w:val="24"/><w:szCs w:val="24"/></w:rPr><w:t xml:space="preserve"> choose to use 10 folder cross validation to check our result. The plotting of the 10 folder cross validation with different number of trees is shown as below:</w:t></w:r></w:p><w:p w14:paraId="23E27350" w14:textId="77777777" w:rsidR="000E4A1E" w:rsidRDefault="000E4A1E" w:rsidP="000E4A1E"><w:pPr><w:pStyle w:val="ListParagraph"/><w:tabs><w:tab w:val="left" w:pos="270"/></w:tabs><w:spacing w:after="0" w:line="240" w:lineRule="auto"/><w:ind w:left="540"/><w:jc w:val="both"/><w:rPr><w:color w:val="FF0000"/><w:sz w:val="24"/><w:szCs w:val="24"/></w:rPr></w:pPr></w:p><w:p w14:paraId="416E882C" w14:textId="77777777" w:rsidR="000E4A1E" w:rsidRPr="008533C7" w:rsidRDefault="000E4A1E" w:rsidP="000E4A1E"><w:pPr><w:pStyle w:val="ListParagraph"/><w:tabs><w:tab w:val="left" w:pos="270"/></w:tabs><w:spacing w:after="0" w:line="240" w:lineRule="auto"/><w:ind w:left="540"/><w:jc w:val="both"/><w:rPr><w:sz w:val="24"/><w:szCs w:val="24"/></w:rPr></w:pPr><w:r w:rsidRPr="00706074"><w:rPr><w:color w:val="FF0000"/><w:sz w:val="24"/><w:szCs w:val="24"/></w:rPr><w:t xml:space="preserve">TODO: </w:t></w:r><w:r><w:rPr><w:sz w:val="24"/><w:szCs w:val="24"/></w:rPr><w:t>T</w:t></w:r><w:r w:rsidRPr="008533C7"><w:rPr><w:sz w:val="24"/><w:szCs w:val="24"/></w:rPr><w:t>ree</w:t></w:r><w:r><w:rPr><w:sz w:val="24"/><w:szCs w:val="24"/></w:rPr><w:t xml:space="preserve"> plot</w:t></w:r></w:p><w:p w14:paraId="486ADE18" w14:textId="77777777" w:rsidR="000E4A1E" w:rsidRPr="008533C7" w:rsidRDefault="000E4A1E" w:rsidP="000E4A1E"><w:pPr><w:pStyle w:val="ListParagraph"/><w:tabs><w:tab w:val="left" w:pos="270"/></w:tabs><w:spacing w:after="0" w:line="240" w:lineRule="auto"/><w:ind w:left="540"/><w:jc w:val="both"/><w:rPr><w:sz w:val="24"/><w:szCs w:val="24"/></w:rPr></w:pPr><w:r w:rsidRPr="00706074"><w:rPr><w:color w:val="FF0000"/><w:sz w:val="24"/><w:szCs w:val="24"/></w:rPr><w:t xml:space="preserve">TODO: </w:t></w:r><w:r w:rsidRPr="008533C7"><w:rPr><w:sz w:val="24"/><w:szCs w:val="24"/></w:rPr><w:t>Analysis of number of trees</w:t></w:r></w:p><w:p w14:paraId="46D71DF4" w14:textId="77777777" w:rsidR="000E4A1E" w:rsidRDefault="000E4A1E" w:rsidP="000E4A1E"><w:pPr><w:pStyle w:val="ListParagraph"/><w:tabs><w:tab w:val="left" w:pos="270"/></w:tabs><w:spacing w:after="0" w:line="240" w:lineRule="auto"/><w:ind w:left="540"/><w:jc w:val="both"/><w:rPr><w:sz w:val="24"/><w:szCs w:val="24"/></w:rPr></w:pPr></w:p><w:p w14:paraId="125D1441" w14:textId="720BCAE0" w:rsidR="00572697" w:rsidRPr="00572697" w:rsidRDefault="00434824" w:rsidP="00572697"><w:pPr><w:pStyle w:val="ListParagraph"/><w:tabs><w:tab w:val="left" w:pos="270"/></w:tabs><w:spacing w:after="0" w:line="240" w:lineRule="auto"/><w:ind w:left="540"/><w:jc w:val="both"/><w:rPr><w:sz w:val="24"/><w:szCs w:val="24"/></w:rPr></w:pPr><w:r><w:rPr><w:sz w:val="24"/><w:szCs w:val="24"/></w:rPr><w:t xml:space="preserve">One big benefit of using </w:t></w:r><w:r w:rsidR="00572697"><w:rPr><w:sz w:val="24"/><w:szCs w:val="24"/></w:rPr><w:t>l</w:t></w:r><w:r><w:rPr><w:sz w:val="24"/><w:szCs w:val="24"/></w:rPr><w:t>ogistic regression instead of random forest is that it can give us the probability of how likely each category can be selected.</w:t></w:r><w:r w:rsidR="00BB11C0"><w:rPr><w:sz w:val="24"/><w:szCs w:val="24"/></w:rPr><w:t xml:space="preserve"> For example: </w:t></w:r><w:r w:rsidR="00BB11C0" w:rsidRPr="00BB11C0"><w:rPr><w:color w:val="FF0000"/><w:sz w:val="24"/><w:szCs w:val="24"/></w:rPr><w:t>TODO</w:t></w:r><w:r w:rsidR="00DC7BEC"><w:rPr><w:color w:val="FF0000"/><w:sz w:val="24"/><w:szCs w:val="24"/></w:rPr><w:t xml:space="preserve"> </w:t></w:r></w:p><w:p w14:paraId="54C7D12F" w14:textId="77777777" w:rsidR="00572697" w:rsidRPr="00572697" w:rsidRDefault="00572697" w:rsidP="00572697"><w:pPr><w:pStyle w:val="ListParagraph"/><w:tabs><w:tab w:val="left" w:pos="270"/></w:tabs><w:spacing w:after="0" w:line="240" w:lineRule="auto"/><w:ind w:left="540"/><w:jc w:val="both"/><w:rPr><w:sz w:val="24"/><w:szCs w:val="24"/></w:rPr></w:pPr></w:p><w:p w14:paraId="10B0D537" w14:textId="00A95328" w:rsidR="00572697" w:rsidRPr="00572697" w:rsidRDefault="00572697" w:rsidP="00572697"><w:pPr><w:pStyle w:val="ListParagraph"/><w:tabs><w:tab w:val="left" w:pos="270"/></w:tabs><w:spacing w:after="0" w:line="240" w:lineRule="auto"/><w:ind w:left="540"/><w:jc w:val="both"/><w:rPr><w:sz w:val="24"/><w:szCs w:val="24"/></w:rPr></w:pPr><w:r w:rsidRPr="00572697"><w:rPr><w:sz w:val="24"/><w:szCs w:val="24"/></w:rPr><w:t>Usually, logistic regression just</w:t></w:r><w:r><w:rPr><w:sz w:val="24"/><w:szCs w:val="24"/></w:rPr><w:t xml:space="preserve"> set a cutoff of 0.5 as the criterion about whether we accept a topic of not. However, in our case, we also have the information of adjective/ noun pair</w:t></w:r><w:r w:rsidR="00CC2B54"><w:rPr><w:sz w:val="24"/><w:szCs w:val="24"/></w:rPr><w:t>s. Hence we make use of both sentence</w:t></w:r><w:r><w:rPr><w:sz w:val="24"/><w:szCs w:val="24"/></w:rPr><w:t xml:space="preserve"> logistic regr</w:t></w:r><w:r w:rsidR="00CC2B54"><w:rPr><w:sz w:val="24"/><w:szCs w:val="24"/></w:rPr><w:t>ession and adjective/ noun pair</w:t></w:r><w:r><w:rPr><w:sz w:val="24"/><w:szCs w:val="24"/></w:rPr><w:t xml:space="preserve"> </w:t></w:r><w:r w:rsidR="00CC2B54"><w:rPr><w:sz w:val="24"/><w:szCs w:val="24"/></w:rPr><w:t>logistic regression, taking 70% weight on adjective/ noun pair logistic regression and 30% weight on sentence logistic regression, and set a new cutoff. After doing this, we found our results improved a lot.</w:t></w:r></w:p><w:p w14:paraId="456BFF3E" w14:textId="77777777" w:rsidR="000E4A1E" w:rsidRDefault="000E4A1E" w:rsidP="00995AD9"><w:pPr><w:pStyle w:val="ListParagraph"/><w:tabs><w:tab w:val="left" w:pos="270"/></w:tabs><w:spacing w:after="0" w:line="240" w:lineRule="auto"/><w:ind w:left="540"/><w:jc w:val="both"/><w:rPr><w:sz w:val="24"/><w:szCs w:val="24"/></w:rPr></w:pPr></w:p><w:p w14:paraId="0B0F7CA4" w14:textId="77777777" w:rsidR="00995AD9" w:rsidRDefault="00995AD9" w:rsidP="00995AD9"><w:pPr><w:pStyle w:val="ListParagraph"/><w:tabs><w:tab w:val="left" w:pos="270"/></w:tabs><w:spacing w:after="0" w:line="240" w:lineRule="auto"/><w:ind w:left="540"/><w:jc w:val="both"/><w:rPr><w:sz w:val="24"/><w:szCs w:val="24"/></w:rPr></w:pPr></w:p><w:p w14:paraId="6C2D66AF" w14:textId="77777777" w:rsidR="00995AD9" w:rsidRDefault="00995AD9" w:rsidP="00995AD9"><w:pPr><w:pStyle w:val="ListParagraph"/><w:tabs><w:tab w:val="left" w:pos="270"/></w:tabs><w:spacing w:after="0" w:line="240" w:lineRule="auto"/><w:ind w:left="540"/><w:jc w:val="both"/><w:rPr><w:sz w:val="24"/><w:szCs w:val="24"/></w:rPr></w:pPr></w:p><w:p w14:paraId="24C92FE0" w14:textId="77777777" w:rsidR="00995AD9" w:rsidRDefault="00995AD9" w:rsidP="00995AD9"><w:pPr><w:pStyle w:val="ListParagraph"/><w:tabs><w:tab w:val="left" w:pos="270"/></w:tabs><w:spacing w:after="0" w:line="240" w:lineRule="auto"/><w:ind w:left="540"/><w:jc w:val="both"/><w:rPr><w:sz w:val="24"/><w:szCs w:val="24"/></w:rPr></w:pPr></w:p><w:p w14:paraId="26DA84C4" w14:textId="4B0EA5D6" w:rsidR="00995AD9" w:rsidRPr="00995AD9" w:rsidRDefault="00995AD9" w:rsidP="00E73206"><w:pPr><w:pStyle w:val="ListParagraph"/><w:numPr><w:ilvl w:val="0"/><w:numId w:val="3"/></w:numPr><w:tabs><w:tab w:val="left" w:pos="270"/></w:tabs><w:spacing w:after="0" w:line="240" w:lineRule="auto"/><w:jc w:val="both"/><w:rPr><w:sz w:val="24"/><w:szCs w:val="24"/></w:rPr></w:pPr><w:r><w:rPr><w:sz w:val="24"/><w:szCs w:val="24"/></w:rPr><w:t>Further Improvements</w:t></w:r><w:r w:rsidR="00591DD0"><w:rPr><w:sz w:val="24"/><w:szCs w:val="24"/></w:rPr><w:t xml:space="preserve"> </w:t></w:r><w:r w:rsidR="00591DD0" w:rsidRPr="00591DD0"><w:rPr><w:sz w:val="24"/><w:szCs w:val="24"/><w:highlight w:val="yellow"/></w:rPr><w:t>AS</w:t></w:r></w:p><w:p w14:paraId="67AA1A05" w14:textId="525D5A71" w:rsidR="00683359" w:rsidRPr="00995AD9" w:rsidRDefault="00683359" w:rsidP="00995AD9"><w:pPr><w:tabs><w:tab w:val="left" w:pos="270"/></w:tabs><w:spacing w:after="0" w:line="240" w:lineRule="auto"/><w:jc w:val="both"/><w:rPr><w:sz w:val="24"/><w:szCs w:val="24"/></w:rPr></w:pPr></w:p><w:p w14:paraId="04225CE7" w14:textId="77777777" w:rsidR="00995AD9" w:rsidRDefault="00995AD9" w:rsidP="00681FA2"><w:pPr><w:tabs><w:tab w:val="num" w:pos="0"/></w:tabs><w:spacing w:after="0" w:line="240" w:lineRule="auto"/><w:ind w:left="180" w:hanging="180"/><w:jc w:val="both"/><w:rPr><w:sz w:val="24"/><w:szCs w:val="24"/></w:rPr></w:pPr></w:p><w:p w14:paraId="3552C869" w14:textId="77777777" w:rsidR="00995AD9" w:rsidRDefault="00995AD9" w:rsidP="00681FA2"><w:pPr><w:tabs><w:tab w:val="num" w:pos="0"/></w:tabs><w:spacing w:after="0" w:line="240" w:lineRule="auto"/><w:ind w:left="180" w:hanging="180"/><w:jc w:val="both"/><w:rPr><w:sz w:val="24"/><w:szCs w:val="24"/></w:rPr></w:pPr></w:p><w:p w14:paraId="65C514E8" w14:textId="77777777" w:rsidR="002C74C1" w:rsidRPr="003341D4" w:rsidRDefault="002C74C1" w:rsidP="00681FA2"><w:pPr><w:tabs><w:tab w:val="num" w:pos="0"/></w:tabs><w:spacing w:after="0" w:line="240" w:lineRule="auto"/><w:ind w:left="180" w:hanging="180"/><w:jc w:val="both"/><w:rPr><w:sz w:val="24"/><w:szCs w:val="24"/></w:rPr></w:pPr></w:p><w:p w14:paraId="03B5189F" w14:textId="38EE021F" w:rsidR="00683359" w:rsidRDefault="00683359" w:rsidP="00681FA2"><w:pPr><w:numPr><w:ilvl w:val="0"/><w:numId w:val="1"/></w:numPr><w:tabs><w:tab w:val="clear" w:pos="720"/><w:tab w:val="num" w:pos="0"/><w:tab w:val="left" w:pos="270"/></w:tabs><w:spacing w:after="0" w:line="240" w:lineRule="auto"/><w:ind w:left="180" w:hanging="180"/><w:jc w:val="both"/><w:rPr><w:b/><w:sz w:val="24"/><w:szCs w:val="24"/></w:rPr></w:pPr><w:r w:rsidRPr="00223EBC"><w:rPr><w:b/><w:sz w:val="24"/><w:szCs w:val="24"/></w:rPr><w:t>Extract adjective and noun pairs out of each meaningful sentence</w:t></w:r><w:r w:rsidR="00591DD0"><w:rPr><w:b/><w:sz w:val="24"/><w:szCs w:val="24"/></w:rPr><w:t xml:space="preserve"> </w:t></w:r><w:r w:rsidR="00591DD0" w:rsidRPr="00591DD0"><w:rPr><w:b/><w:sz w:val="24"/><w:szCs w:val="24"/><w:highlight w:val="yellow"/></w:rPr><w:t>Toby</w:t></w:r></w:p><w:p w14:paraId="54BFEE08" w14:textId="77777777" w:rsidR="002C74C1" w:rsidRPr="00223EBC" w:rsidRDefault="002C74C1" w:rsidP="002C74C1"><w:pPr><w:tabs><w:tab w:val="left" w:pos="270"/></w:tabs><w:spacing w:after="0" w:line="240" w:lineRule="auto"/><w:ind w:left="180"/><w:jc w:val="both"/><w:rPr><w:b/><w:sz w:val="24"/><w:szCs w:val="24"/></w:rPr></w:pPr></w:p><w:p w14:paraId="557E4754" w14:textId="77777777" w:rsidR="00683359" w:rsidRDefault="00683359" w:rsidP="00681FA2"><w:pPr><w:tabs><w:tab w:val="num" w:pos="0"/></w:tabs><w:spacing w:after="0" w:line="240" w:lineRule="auto"/><w:ind w:left="180" w:hanging="180"/><w:jc w:val="both"/><w:rPr><w:sz w:val="24"/><w:szCs w:val="24"/></w:rPr></w:pPr><w:r><w:rPr><w:sz w:val="24"/><w:szCs w:val="24"/></w:rPr><w:tab/><w:t>Notice in the example above that the insights we wish to extract are in the form of adjective-noun pairs</w:t></w:r><w:r><w:rPr><w:rFonts w:hint="eastAsia"/><w:sz w:val="24"/><w:szCs w:val="24"/></w:rPr><w:t xml:space="preserve">. We use a package named </w:t></w:r><w:r><w:rPr><w:sz w:val="24"/><w:szCs w:val="24"/></w:rPr><w:t>“</w:t></w:r><w:r><w:rPr><w:rFonts w:hint="eastAsia"/><w:sz w:val="24"/><w:szCs w:val="24"/></w:rPr><w:t>Spacy</w:t></w:r><w:r><w:rPr><w:sz w:val="24"/><w:szCs w:val="24"/></w:rPr><w:t>”</w:t></w:r><w:r><w:rPr><w:rFonts w:hint="eastAsia"/><w:sz w:val="24"/><w:szCs w:val="24"/></w:rPr><w:t xml:space="preserve"> to parse </w:t></w:r><w:r><w:rPr><w:sz w:val="24"/><w:szCs w:val="24"/></w:rPr><w:t xml:space="preserve">each sentence into </w:t></w:r><w:r><w:rPr><w:rFonts w:hint="eastAsia"/><w:sz w:val="24"/><w:szCs w:val="24"/></w:rPr><w:t>a dependency tree in order to inform part of speech tagging. If a noun is the subject of the adjective, this noun shares the same head with the adjective. Therefore, we can use</w:t></w:r><w:r><w:rPr><w:sz w:val="24"/><w:szCs w:val="24"/></w:rPr><w:t xml:space="preserve"> the</w:t></w:r><w:r><w:rPr><w:rFonts w:hint="eastAsia"/><w:sz w:val="24"/><w:szCs w:val="24"/></w:rPr><w:t xml:space="preserve"> dependency tree to </w:t></w:r><w:r><w:rPr><w:sz w:val="24"/><w:szCs w:val="24"/></w:rPr><w:t>identify noun-adjective associations</w:t></w:r><w:r><w:rPr><w:rFonts w:hint="eastAsia"/><w:sz w:val="24"/><w:szCs w:val="24"/></w:rPr><w:t>.</w:t></w:r></w:p><w:p w14:paraId="621B9C5E" w14:textId="77777777" w:rsidR="002C74C1" w:rsidRPr="003341D4" w:rsidRDefault="002C74C1" w:rsidP="00681FA2"><w:pPr><w:tabs><w:tab w:val="num" w:pos="0"/></w:tabs><w:spacing w:after="0" w:line="240" w:lineRule="auto"/><w:ind w:left="180" w:hanging="180"/><w:jc w:val="both"/><w:rPr><w:sz w:val="24"/><w:szCs w:val="24"/></w:rPr></w:pPr></w:p><w:p w14:paraId="68834ADD" w14:textId="3D4FA3C1" w:rsidR="00683359" w:rsidRDefault="00683359" w:rsidP="00681FA2"><w:pPr><w:numPr><w:ilvl w:val="0"/><w:numId w:val="1"/></w:numPr><w:tabs><w:tab w:val="clear" w:pos="720"/><w:tab w:val="num" w:pos="0"/><w:tab w:val="left" w:pos="270"/></w:tabs><w:spacing w:after="0" w:line="240" w:lineRule="auto"/><w:ind w:left="180" w:hanging="180"/><w:jc w:val="both"/><w:rPr><w:b/><w:sz w:val="24"/><w:szCs w:val="24"/></w:rPr></w:pPr><w:r w:rsidRPr="00223EBC"><w:rPr><w:b/><w:sz w:val="24"/><w:szCs w:val="24"/></w:rPr><w:t>Perform sentiment analysis to provide sentiment scores from 0 (negative) to 1 (positive)</w:t></w:r><w:r w:rsidR="00591DD0"><w:rPr><w:b/><w:sz w:val="24"/><w:szCs w:val="24"/></w:rPr><w:t xml:space="preserve"> </w:t></w:r><w:r w:rsidR="00591DD0" w:rsidRPr="00591DD0"><w:rPr><w:b/><w:sz w:val="24"/><w:szCs w:val="24"/><w:highlight w:val="yellow"/></w:rPr><w:t>Fox</w:t></w:r></w:p><w:p w14:paraId="7A47A5D4" w14:textId="77777777" w:rsidR="003B44A4" w:rsidRPr="00223EBC" w:rsidRDefault="003B44A4" w:rsidP="003B44A4"><w:pPr><w:tabs><w:tab w:val="left" w:pos="270"/></w:tabs><w:spacing w:after="0" w:line="240" w:lineRule="auto"/><w:ind w:left="180"/><w:jc w:val="both"/><w:rPr><w:b/><w:sz w:val="24"/><w:szCs w:val="24"/></w:rPr></w:pPr></w:p><w:p w14:paraId="0FDBE8F7" w14:textId="77777777" w:rsidR="00683359" w:rsidRDefault="00683359" w:rsidP="00681FA2"><w:pPr><w:tabs><w:tab w:val="num" w:pos="0"/></w:tabs><w:spacing w:after="0" w:line="240" w:lineRule="auto"/><w:ind w:left="180" w:hanging="180"/><w:jc w:val="both"/><w:rPr><w:sz w:val="24"/><w:szCs w:val="24"/></w:rPr></w:pPr><w:r><w:rPr><w:sz w:val="24"/><w:szCs w:val="24"/></w:rPr><w:tab/><w:t>A key advantage of the organization of the reviews in this dataset is that each review is known to be a response to either the “what I loved” or “what to know” sections of the questionnaire. This information can be used to help infer the type of sentiment expressed in the review. We propose a Bayesian approach for combining this prior information with the proposed adjective sentiment score that is calculated using NLTK. A potential model is to assume a normally distributed prior with a mean of 0.3 for the sentiment of reviews from “what to know” and 0.8 for the sentiment of reviews from “what I loved,” in combination with a normal likelihood based on the text analysis.</w:t></w:r></w:p><w:p w14:paraId="758D286A" w14:textId="77777777" w:rsidR="003B44A4" w:rsidRDefault="003B44A4" w:rsidP="00681FA2"><w:pPr><w:tabs><w:tab w:val="num" w:pos="0"/></w:tabs><w:spacing w:after="0" w:line="240" w:lineRule="auto"/><w:ind w:left="180" w:hanging="180"/><w:jc w:val="both"/><w:rPr><w:sz w:val="24"/><w:szCs w:val="24"/></w:rPr></w:pPr></w:p><w:p w14:paraId="0284F5B2" w14:textId="1C7F2CCB" w:rsidR="00683359" w:rsidRDefault="00683359" w:rsidP="00681FA2"><w:pPr><w:pStyle w:val="ListParagraph"/><w:numPr><w:ilvl w:val="0"/><w:numId w:val="1"/></w:numPr><w:tabs><w:tab w:val="clear" w:pos="720"/><w:tab w:val="num" w:pos="0"/><w:tab w:val="left" w:pos="270"/></w:tabs><w:spacing w:after="0" w:line="240" w:lineRule="auto"/><w:ind w:left="180" w:hanging="180"/><w:jc w:val="both"/><w:rPr><w:b/><w:sz w:val="24"/><w:szCs w:val="24"/></w:rPr></w:pPr><w:r w:rsidRPr="00223EBC"><w:rPr><w:b/><w:sz w:val="24"/><w:szCs w:val="24"/></w:rPr><w:t>Enhance user experience by displaying straightforward and informative overview of the key aspects of each hotel</w:t></w:r><w:r w:rsidR="00591DD0"><w:rPr><w:b/><w:sz w:val="24"/><w:szCs w:val="24"/></w:rPr><w:t xml:space="preserve"> </w:t></w:r><w:r w:rsidR="00591DD0" w:rsidRPr="00591DD0"><w:rPr><w:b/><w:sz w:val="24"/><w:szCs w:val="24"/><w:highlight w:val="yellow"/></w:rPr><w:t>Fox</w:t></w:r></w:p><w:p w14:paraId="4354708E" w14:textId="77777777" w:rsidR="003B44A4" w:rsidRPr="00223EBC" w:rsidRDefault="003B44A4" w:rsidP="003B44A4"><w:pPr><w:pStyle w:val="ListParagraph"/><w:tabs><w:tab w:val="left" w:pos="270"/></w:tabs><w:spacing w:after="0" w:line="240" w:lineRule="auto"/><w:ind w:left="180"/><w:jc w:val="both"/><w:rPr><w:b/><w:sz w:val="24"/><w:szCs w:val="24"/></w:rPr></w:pPr></w:p><w:p w14:paraId="41D2565A" w14:textId="77777777" w:rsidR="00683359" w:rsidRDefault="00683359" w:rsidP="00681FA2"><w:pPr><w:tabs><w:tab w:val="num" w:pos="0"/></w:tabs><w:spacing w:after="0" w:line="240" w:lineRule="auto"/><w:ind w:left="180" w:hanging="180"/><w:jc w:val="both"/><w:rPr><w:sz w:val="24"/><w:szCs w:val="24"/></w:rPr></w:pPr><w:r><w:rPr><w:sz w:val="24"/><w:szCs w:val="24"/></w:rPr><w:tab/><w:t>A fully optimized data structure is created that provides the capability and functionality to store all of the extracted keywords, adjectives, and sentiment scores into corresponding classified categories for each hotel. This information will be presented in summary, with the option of full output, for ease of use by Trip Advisor. Visualizations will be presented with the text output for further insight (e.g. identifying trends).</w:t></w:r></w:p><w:p w14:paraId="3D478660" w14:textId="77777777" w:rsidR="00683359" w:rsidRDefault="00683359" w:rsidP="00681FA2"><w:pPr><w:spacing w:after="0" w:line="240" w:lineRule="auto"/><w:jc w:val="both"/><w:rPr><w:sz w:val="24"/><w:szCs w:val="24"/></w:rPr></w:pPr></w:p><w:p w14:paraId="3A7CE1BD" w14:textId="77777777" w:rsidR="001413D4" w:rsidRDefault="001413D4" w:rsidP="00681FA2"><w:pPr><w:spacing w:after="0" w:line="240" w:lineRule="auto"/><w:jc w:val="both"/><w:rPr><w:sz w:val="24"/><w:szCs w:val="24"/></w:rPr></w:pPr></w:p><w:p w14:paraId="63ECD8B7" w14:textId="77777777" w:rsidR="001413D4" w:rsidRDefault="001413D4" w:rsidP="00681FA2"><w:pPr><w:spacing w:after="0" w:line="240" w:lineRule="auto"/><w:jc w:val="both"/><w:rPr><w:sz w:val="24"/><w:szCs w:val="24"/></w:rPr></w:pPr></w:p><w:p w14:paraId="3A7AF65E" w14:textId="77777777" w:rsidR="00E43E79" w:rsidRPr="005E32A5" w:rsidRDefault="00E43E79" w:rsidP="00E43E79"><w:pPr><w:jc w:val="both"/><w:rPr><w:rFonts w:ascii="Times" w:hAnsi="Times"/><w:b/><w:sz w:val="26"/><w:szCs w:val="26"/><w:u w:val="single"/></w:rPr></w:pPr><w:r w:rsidRPr="005E32A5"><w:rPr><w:rFonts w:ascii="Times" w:hAnsi="Times"/><w:b/><w:sz w:val="26"/><w:szCs w:val="26"/><w:u w:val="single"/></w:rPr><w:t>Results</w:t></w:r></w:p><w:p w14:paraId="232F725D" w14:textId="77777777" w:rsidR="00552C27" w:rsidRDefault="00552C27" w:rsidP="00552C27"><w:pPr><w:spacing w:after="0" w:line="240" w:lineRule="auto"/><w:jc w:val="both"/><w:rPr><w:sz w:val="24"/><w:szCs w:val="24"/></w:rPr></w:pPr></w:p><w:p w14:paraId="6E431068" w14:textId="77777777" w:rsidR="00552C27" w:rsidRDefault="00552C27" w:rsidP="00552C27"><w:pPr><w:spacing w:after="0" w:line="240" w:lineRule="auto"/><w:jc w:val="both"/><w:rPr><w:sz w:val="24"/><w:szCs w:val="24"/></w:rPr></w:pPr></w:p><w:p w14:paraId="1DD94F95" w14:textId="77777777" w:rsidR="00552C27" w:rsidRDefault="00552C27" w:rsidP="00552C27"><w:pPr><w:spacing w:after="0" w:line="240" w:lineRule="auto"/><w:jc w:val="both"/><w:rPr><w:sz w:val="24"/><w:szCs w:val="24"/></w:rPr></w:pPr></w:p><w:p w14:paraId="48F68B94" w14:textId="77777777" w:rsidR="00E43E79" w:rsidRPr="00AA167D" w:rsidRDefault="00E43E79" w:rsidP="00E43E79"><w:pPr><w:jc w:val="both"/><w:rPr><w:rFonts w:ascii="Times" w:hAnsi="Times"/><w:b/><w:sz w:val="26"/><w:szCs w:val="26"/><w:u w:val="single"/></w:rPr></w:pPr><w:r w:rsidRPr="00AA167D"><w:rPr><w:rFonts w:ascii="Times" w:hAnsi="Times"/><w:b/><w:sz w:val="26"/><w:szCs w:val="26"/><w:u w:val="single"/></w:rPr><w:t>Reference</w:t></w:r></w:p><w:p w14:paraId="645F2A25" w14:textId="77777777" w:rsidR="00AA167D" w:rsidRDefault="00AA167D" w:rsidP="00AA167D"><w:pPr><w:spacing w:after="0" w:line="240" w:lineRule="auto"/><w:jc w:val="both"/><w:rPr><w:sz w:val="24"/><w:szCs w:val="24"/></w:rPr></w:pPr></w:p><w:p w14:paraId="31E0B990" w14:textId="77777777" w:rsidR="00AA167D" w:rsidRDefault="00AA167D" w:rsidP="00AA167D"><w:pPr><w:spacing w:after="0" w:line="240" w:lineRule="auto"/><w:jc w:val="both"/><w:rPr><w:sz w:val="24"/><w:szCs w:val="24"/></w:rPr></w:pPr></w:p><w:p w14:paraId="153BA747" w14:textId="77777777" w:rsidR="00AA167D" w:rsidRDefault="00AA167D" w:rsidP="00AA167D"><w:pPr><w:spacing w:after="0" w:line="240" w:lineRule="auto"/><w:jc w:val="both"/><w:rPr><w:sz w:val="24"/><w:szCs w:val="24"/></w:rPr></w:pPr></w:p><w:p w14:paraId="0457E1C4" w14:textId="77777777" w:rsidR="001413D4" w:rsidRDefault="001413D4" w:rsidP="00AA167D"><w:pPr><w:spacing w:after="0" w:line="240" w:lineRule="auto"/><w:jc w:val="both"/></w:pPr></w:p><w:sectPr w:rsidR="001413D4" w:rsidSect="00D87F3F"><w:pgSz w:w="12240" w:h="15840"/><w:pgMar w:top="1224" w:right="1440" w:bottom="1440" w:left="1440" w:header="720" w:footer="720" w:gutter="0"/><w:cols w:space="720"/><w:docGrid w:linePitch="360"/></w:sectPr></w:body></w:document>